{"caption":"","code":"pkBLldm2aS","dimensions":{"height":640,"width":640},"display_url":"https://scontent-lht6-1.cdninstagram.com/vp/728dfffdb45e62c18602493f8559443e/5B11E78D/t51.2885-15/e15/10483428_737318436325235_528675147_n.jpg","id":"748728632236271250","is_video":false,"location":{"has_public_page":true,"id":"847544201","name":"Mulbuie","slug":"mulbuie"},"media_url":"https://scontent-lht6-1.cdninstagram.com/vp/728dfffdb45e62c18602493f8559443e/5B11E78D/t51.2885-15/e15/10483428_737318436325235_528675147_n.jpg","post_url":"https://www.instagram.com/p/pkBLldm2aS","tags":[],"timestamp":1403475430,"FullID":"2014-06-22-748728632236271250","lat":57.5406396333,"long":-4.4284455333,"location_count":217}