{"caption":"#road #landscape #lakedistrict","code":"xMbL2Km2Ti","dimensions":{"height":640,"width":640},"display_url":"https://scontent-lht6-1.cdninstagram.com/vp/6da9e11e8939597416b2bc6dd28fd911/5B0F8DBC/t51.2885-15/e15/10891077_1538885793019246_1157985261_n.jpg","id":"886202788015203554","is_video":false,"location":{"has_public_page":true,"id":"469973249","name":"Lake District","slug":"lake-district"},"media_url":"https://scontent-lht6-1.cdninstagram.com/vp/6da9e11e8939597416b2bc6dd28fd911/5B0F8DBC/t51.2885-15/e15/10891077_1538885793019246_1157985261_n.jpg","post_url":"https://www.instagram.com/p/xMbL2Km2Ti","tags":["#road","#landscape","#lakedistrict"],"timestamp":1419863626,"FullID":"2014-12-29-886202788015203554","lat":54.5,"long":-3.1666666667,"location_count":43}