{"caption":"Bicycle roundabout #bike #museum #blackandwhite #lookingup #shotonmoment #teampixel","code":"BvFJhyZA_gO","dimensions":{"height":1080,"width":1080},"display_url":"https://scontent-mia3-1.cdninstagram.com/vp/6d45ac8c3f6a8994979a3b86c6df4083/5D0A59A9/t51.2885-15/e35/52851253_563211157533062_3717533470403766602_n.jpg?_nc_ht=scontent-mia3-1.cdninstagram.com","id":"2001047513704167438","is_video":false,"location":{"has_public_page":true,"id":"3441594","name":"Riverside Museum","slug":"riverside-museum"},"media_url":"https://scontent-mia3-1.cdninstagram.com/vp/6d45ac8c3f6a8994979a3b86c6df4083/5D0A59A9/t51.2885-15/e35/52851253_563211157533062_3717533470403766602_n.jpg?_nc_ht=scontent-mia3-1.cdninstagram.com","post_url":"https://www.instagram.com/p/BvFJhyZA_gO","tags":["#bike","#museum","#blackandwhite","#lookingup","#shotonmoment","#teampixel"],"timestamp":1552763474,"FullID":"2019-03-16-2001047513704167438","lat":55.8654509214,"long":-4.3059019297,"location_count":1}