{"name":"sunset","posts":[{"caption":"The ridge #landscape #x100f #mountains #ridge #sunset #valley #view #clouds #sky","code":"CWRR9pVrCqv","dimensions":{"height":1080,"width":1080},"display_url":"https://scontent-lhr8-1.cdninstagram.com/v/t51.2885-15/e35/s1080x1080/256783026_2934093330234392_7477544663410160275_n.jpg?_nc_ht=scontent-lhr8-1.cdninstagram.com\u0026_nc_cat=108\u0026_nc_ohc=LOMZ7WtuzyQAX9HlqvC\u0026edm=AABBvjUBAAAA\u0026ccb=7-4\u0026oh=29cc7ebf56b56edddc31c38ac63b4662\u0026oe=61997150\u0026_nc_sid=83d603","id":"2707023854092167855","is_video":false,"location":{"has_public_page":true,"id":"953419235","name":"Dove Crag","slug":"dove-crag"},"media_url":"https://scontent-lhr8-1.cdninstagram.com/v/t51.2885-15/e35/s1080x1080/256783026_2934093330234392_7477544663410160275_n.jpg?_nc_ht=scontent-lhr8-1.cdninstagram.com\u0026_nc_cat=108\u0026_nc_ohc=LOMZ7WtuzyQAX9HlqvC\u0026edm=AABBvjUBAAAA\u0026ccb=7-4\u0026oh=29cc7ebf56b56edddc31c38ac63b4662\u0026oe=61997150\u0026_nc_sid=83d603","post_url":"https://instagram.com/p/CWRR9pVrCqv","tags":["#landscape","#x100f","#mountains","#ridge","#sunset","#valley","#view","#clouds","#sky"],"timestamp":1636922412,"FullID":"2021-11-14-2707023854092167855","lat":54.4850611111,"long":-2.9677694444,"location_count":3},{"caption":"Wells-next-the-sea #sunset #seaside #cloud #dusk #boats","code":"CVtMSCJLp7D","dimensions":{"height":1080,"width":1080},"display_url":"https://scontent-lhr8-1.cdninstagram.com/v/t51.2885-15/e35/s1080x1080/250988761_1280274752434008_2192975856253634794_n.jpg?_nc_ht=scontent-lhr8-1.cdninstagram.com\u0026_nc_cat=100\u0026_nc_ohc=Q8ajafrwYfMAX_h_VUU\u0026edm=AABBvjUBAAAA\u0026ccb=7-4\u0026oh=6b82c726ba481627a5677e5d83e8b3dd\u0026oe=6186E533\u0026_nc_sid=83d603","id":"2696865767675043523","is_video":false,"location":{"has_public_page":true,"id":"203889106311708","name":"Wells Next to Sea","slug":"wells-next-to-sea"},"media_url":"https://scontent-lhr8-1.cdninstagram.com/v/t51.2885-15/e35/s1080x1080/250988761_1280274752434008_2192975856253634794_n.jpg?_nc_ht=scontent-lhr8-1.cdninstagram.com\u0026_nc_cat=100\u0026_nc_ohc=Q8ajafrwYfMAX_h_VUU\u0026edm=AABBvjUBAAAA\u0026ccb=7-4\u0026oh=6b82c726ba481627a5677e5d83e8b3dd\u0026oe=6186E533\u0026_nc_sid=83d603","post_url":"https://instagram.com/p/CVtMSCJLp7D","tags":["#sunset","#seaside","#cloud","#dusk","#boats"],"timestamp":1635711473,"FullID":"2021-10-31-2696865767675043523","lat":52.9737883333,"long":0.8477333333,"location_count":1},{"caption":"Ex birb #feather #sunset #fluff #texture #X100f","code":"CVnS12cohy7","dimensions":{"height":1080,"width":1080},"display_url":"https://scontent-lhr8-2.cdninstagram.com/v/t51.2885-15/e35/249480419_933686153902549_5919269926448783332_n.jpg?_nc_ht=scontent-lhr8-2.cdninstagram.com\u0026_nc_cat=101\u0026_nc_ohc=hIxfPrnTORsAX9b-8Cl\u0026edm=AABBvjUBAAAA\u0026ccb=7-4\u0026oh=9fb7e0717b046177239bacf66eb5a0f7\u0026oe=6186614A\u0026_nc_sid=83d603","id":"2695205767436442811","is_video":false,"location":{"has_public_page":true,"id":"279282566","name":"Burnham Overy","slug":"burnham-overy"},"media_url":"https://scontent-lhr8-2.cdninstagram.com/v/t51.2885-15/e35/249480419_933686153902549_5919269926448783332_n.jpg?_nc_ht=scontent-lhr8-2.cdninstagram.com\u0026_nc_cat=101\u0026_nc_ohc=hIxfPrnTORsAX9b-8Cl\u0026edm=AABBvjUBAAAA\u0026ccb=7-4\u0026oh=9fb7e0717b046177239bacf66eb5a0f7\u0026oe=6186614A\u0026_nc_sid=83d603","post_url":"https://instagram.com/p/CVnS12cohy7","tags":["#feather","#sunset","#fluff","#texture","#X100f"],"timestamp":1635513586,"FullID":"2021-10-29-2695205767436442811","lat":52.9572,"long":0.7422694444,"location_count":2},{"caption":"Porthmeor Beach #beach #view #town #hill #sunset #landscape","code":"CTF87jEgUS5","dimensions":{"height":1080,"width":1080},"display_url":"https://instagram.flhr3-3.fna.fbcdn.net/v/t51.2885-15/e35/s1080x1080/240776470_4331961756841486_4865694139448586340_n.jpg?_nc_ht=instagram.flhr3-3.fna.fbcdn.net\u0026_nc_cat=110\u0026_nc_ohc=jJbnxhom_nwAX93sejY\u0026edm=AABBvjUBAAAA\u0026ccb=7-4\u0026oh=f0a04b8925febdaba662b24461948f78\u0026oe=612F988B\u0026_nc_sid=83d603","id":"2649791930673743033","is_video":false,"location":{"has_public_page":true,"id":"1034734605","name":"Porthmeor Beach","slug":"porthmeor-beach"},"media_url":"https://instagram.flhr3-3.fna.fbcdn.net/v/t51.2885-15/e35/s1080x1080/240776470_4331961756841486_4865694139448586340_n.jpg?_nc_ht=instagram.flhr3-3.fna.fbcdn.net\u0026_nc_cat=110\u0026_nc_ohc=jJbnxhom_nwAX93sejY\u0026edm=AABBvjUBAAAA\u0026ccb=7-4\u0026oh=f0a04b8925febdaba662b24461948f78\u0026oe=612F988B\u0026_nc_sid=83d603","post_url":"https://instagram.com/p/CTF87jEgUS5","tags":["#beach","#view","#town","#hill","#sunset","#landscape"],"timestamp":1630099835,"FullID":"2021-08-27-2649791930673743033","lat":50.21444,"long":-5.48466,"location_count":1},{"caption":"I took a photo of this same view a few days ago but forgot to post it. Came back today when we had a much better sunset, glad I waited. #sunset #tree #sky #view #blue #orange #clouds #snow #x100f","code":"CJgnaXCrw1J","dimensions":{"height":1080,"width":1080},"display_url":"https://scontent-lht6-1.cdninstagram.com/v/t51.2885-15/e35/s1080x1080/133872652_196614158783850_3736905563865677643_n.jpg?_nc_ht=scontent-lht6-1.cdninstagram.com\u0026_nc_cat=106\u0026_nc_ohc=BtgXkMUg1eUAX_4gQOL\u0026tp=1\u0026oh=7bc1507d4e9f32d154e05fb647595585\u0026oe=6016F341","id":"2477153130315189577","is_video":false,"location":{"has_public_page":true,"id":"246994238","name":"Muir Of Ord, Highland, United Kingdom","slug":"muir-of-ord-highland-united-kingdom"},"media_url":"https://scontent-lht6-1.cdninstagram.com/v/t51.2885-15/e35/s1080x1080/133872652_196614158783850_3736905563865677643_n.jpg?_nc_ht=scontent-lht6-1.cdninstagram.com\u0026_nc_cat=106\u0026_nc_ohc=BtgXkMUg1eUAX_4gQOL\u0026tp=1\u0026oh=7bc1507d4e9f32d154e05fb647595585\u0026oe=6016F341","post_url":"https://instagram.com/p/CJgnaXCrw1J","tags":["#sunset","#tree","#sky","#view","#blue","#orange","#clouds","#snow","#x100f"],"timestamp":1609519686,"FullID":"2021-01-01-2477153130315189577","lat":57.5167,"long":-4.45,"location_count":26},{"caption":"Feel like I’ve taken this photo a 100 times. But this time it has a boat. 🚢 #landscape #view #boat #sunset #clouds #blue #sky #orange #x100f #reflection #shore #sea","code":"CJWXjrpLjqU","dimensions":{"height":1080,"width":1080},"display_url":"https://scontent-lhr8-1.cdninstagram.com/v/t51.2885-15/e35/s1080x1080/133102757_4191755020853167_7184930686216253958_n.jpg?_nc_ht=scontent-lhr8-1.cdninstagram.com\u0026_nc_cat=107\u0026_nc_ohc=MexQPGk5_qIAX9C1dFP\u0026tp=1\u0026oh=8fffc9598dd09a26fe093e87d2c52049\u0026oe=6012C3E7","id":"2474268652399901332","is_video":false,"location":{"has_public_page":true,"id":"135178416515306","name":"Redcastle","slug":"redcastle"},"media_url":"https://scontent-lhr8-1.cdninstagram.com/v/t51.2885-15/e35/s1080x1080/133102757_4191755020853167_7184930686216253958_n.jpg?_nc_ht=scontent-lhr8-1.cdninstagram.com\u0026_nc_cat=107\u0026_nc_ohc=MexQPGk5_qIAX9C1dFP\u0026tp=1\u0026oh=8fffc9598dd09a26fe093e87d2c52049\u0026oe=6012C3E7","post_url":"https://instagram.com/p/CJWXjrpLjqU","tags":["#landscape","#view","#boat","#sunset","#clouds","#blue","#sky","#orange","#x100f","#reflection","#shore","#sea"],"timestamp":1609175829,"FullID":"2020-12-28-2474268652399901332","lat":57.513463,"long":-4.3657329,"location_count":7},{"caption":"Oil rigs at Cromarty keep getting closer #oilrig #sea #oil #northsea #sky #clouds #sunset #orange #x100f","code":"CJVi--erCJh","dimensions":{"height":1080,"width":1080},"display_url":"https://scontent-lhr8-2.cdninstagram.com/v/t51.2885-15/e35/s1080x1080/133852805_2834643326823062_8345321735236628451_n.jpg?_nc_ht=scontent-lhr8-2.cdninstagram.com\u0026_nc_cat=102\u0026_nc_ohc=Nb7MjJAiQKcAX-PYF9J\u0026tp=1\u0026oh=b36167061334d3a2c9ad7b391d20fc84\u0026oe=6011A158","id":"2474037431585481313","is_video":false,"location":{"has_public_page":true,"id":"254970202","name":"Cromarty, Highland, United Kingdom","slug":"cromarty-highland-united-kingdom"},"media_url":"https://scontent-lhr8-2.cdninstagram.com/v/t51.2885-15/e35/s1080x1080/133852805_2834643326823062_8345321735236628451_n.jpg?_nc_ht=scontent-lhr8-2.cdninstagram.com\u0026_nc_cat=102\u0026_nc_ohc=Nb7MjJAiQKcAX-PYF9J\u0026tp=1\u0026oh=b36167061334d3a2c9ad7b391d20fc84\u0026oe=6011A158","post_url":"https://instagram.com/p/CJVi--erCJh","tags":["#oilrig","#sea","#oil","#northsea","#sky","#clouds","#sunset","#orange","#x100f"],"timestamp":1609148266,"FullID":"2020-12-28-2474037431585481313","lat":57.6667,"long":-4.03333,"location_count":6},{"caption":"Christmas Walkies 🐾 #field #view #sunset #green #grass #trees #x100f #landscape","code":"CJOfAzMLh6Q","dimensions":{"height":1080,"width":1080},"display_url":"https://scontent-lhr8-1.cdninstagram.com/v/t51.2885-15/e35/s1080x1080/132597473_178270637339674_4596333261681692083_n.jpg?_nc_ht=scontent-lhr8-1.cdninstagram.com\u0026_nc_cat=110\u0026_nc_ohc=0mD0WOcf1fkAX-Ren_S\u0026tp=1\u0026oh=c90058fc984ed8c3fa1899660939922d\u0026oe=600E5F8F","id":"2472049639880007312","is_video":false,"location":{"has_public_page":true,"id":"246994238","name":"Muir Of Ord, Highland, United Kingdom","slug":"muir-of-ord-highland-united-kingdom"},"media_url":"https://scontent-lhr8-1.cdninstagram.com/v/t51.2885-15/e35/s1080x1080/132597473_178270637339674_4596333261681692083_n.jpg?_nc_ht=scontent-lhr8-1.cdninstagram.com\u0026_nc_cat=110\u0026_nc_ohc=0mD0WOcf1fkAX-Ren_S\u0026tp=1\u0026oh=c90058fc984ed8c3fa1899660939922d\u0026oe=600E5F8F","post_url":"https://instagram.com/p/CJOfAzMLh6Q","tags":["#field","#view","#sunset","#green","#grass","#trees","#x100f","#landscape"],"timestamp":1608911303,"FullID":"2020-12-25-2472049639880007312","lat":57.5167,"long":-4.45,"location_count":26},{"caption":"Dancing as the sun goes down, at 15:00 #landscape #view #sea #firth #field #tree #sunset #green #x100f","code":"CJMRavJrWiz","dimensions":{"height":1080,"width":1080},"display_url":"https://scontent-lhr8-1.cdninstagram.com/v/t51.2885-15/e35/s1080x1080/132329007_399412497812662_6131534496344544134_n.jpg?_nc_ht=scontent-lhr8-1.cdninstagram.com\u0026_nc_cat=110\u0026_nc_ohc=SwpthiulLR4AX-F3m60\u0026tp=1\u0026oh=b66182b608b22f2676a08a9fab635201\u0026oe=60103960","id":"2471426899644868787","is_video":false,"location":{"has_public_page":true,"id":"236467102","name":"Munlochy, Highland, United Kingdom","slug":"munlochy-highland-united-kingdom"},"media_url":"https://scontent-lhr8-1.cdninstagram.com/v/t51.2885-15/e35/s1080x1080/132329007_399412497812662_6131534496344544134_n.jpg?_nc_ht=scontent-lhr8-1.cdninstagram.com\u0026_nc_cat=110\u0026_nc_ohc=SwpthiulLR4AX-F3m60\u0026tp=1\u0026oh=b66182b608b22f2676a08a9fab635201\u0026oe=60103960","post_url":"https://instagram.com/p/CJMRavJrWiz","tags":["#landscape","#view","#sea","#firth","#field","#tree","#sunset","#green","#x100f"],"timestamp":1608837066,"FullID":"2020-12-24-2471426899644868787","lat":57.54957,"long":-4.26103,"location_count":2},{"caption":"Next stop: Inverness. #train #travel #window #blur #shotoniphone #sunset #evening #sky","code":"CDMwBXsg0ol","dimensions":{"height":1080,"width":1080},"display_url":"https://scontent-lhr8-1.cdninstagram.com/v/t51.2885-15/e35/s1080x1080/115958983_185114796311615_9202098891734596523_n.jpg?_nc_ht=scontent-lhr8-1.cdninstagram.com\u0026_nc_cat=111\u0026_nc_ohc=_j7xATC7JRoAX8pLU28\u0026oh=ce381b6800faf27cdd79631f3548a58e\u0026oe=5F4A6520","id":"2363475104857541157","is_video":false,"location":{"has_public_page":true,"id":"2703726","name":"Emirates Stadium","slug":"emirates-stadium"},"media_url":"https://scontent-lhr8-1.cdninstagram.com/v/t51.2885-15/e35/s1080x1080/115958983_185114796311615_9202098891734596523_n.jpg?_nc_ht=scontent-lhr8-1.cdninstagram.com\u0026_nc_cat=111\u0026_nc_ohc=_j7xATC7JRoAX8pLU28\u0026oh=ce381b6800faf27cdd79631f3548a58e\u0026oe=5F4A6520","post_url":"https://instagram.com/p/CDMwBXsg0ol","tags":["#train","#travel","#window","#blur","#shotoniphone","#sunset","#evening","#sky"],"timestamp":1595968209,"FullID":"2020-07-28-2363475104857541157","lat":51.5550515453,"long":-0.108473235,"location_count":1},{"caption":"Good Evening #window #evening #sun #light #sunset #orange #shotoniphone","code":"CBOZKZLgPYU","dimensions":{"height":1080,"width":1080},"display_url":"https://scontent-lhr8-1.cdninstagram.com/v/t51.2885-15/e35/s1080x1080/102657121_267388707833663_2449706669837304887_n.jpg?_nc_ht=scontent-lhr8-1.cdninstagram.com\u0026_nc_cat=111\u0026_nc_ohc=kBOrqpCDS-YAX8aWULg\u0026oh=f81cea1f4cc4a311684473212158f556\u0026oe=5F29AC35","id":"2327908722791216660","is_video":false,"location":{"has_public_page":true,"id":"222039596","name":"Archway, London","slug":"archway-london"},"media_url":"https://scontent-lhr8-1.cdninstagram.com/v/t51.2885-15/e35/s1080x1080/102657121_267388707833663_2449706669837304887_n.jpg?_nc_ht=scontent-lhr8-1.cdninstagram.com\u0026_nc_cat=111\u0026_nc_ohc=kBOrqpCDS-YAX8aWULg\u0026oh=f81cea1f4cc4a311684473212158f556\u0026oe=5F29AC35","post_url":"https://www.instagram.com/p/CBOZKZLgPYU","tags":["#window","#evening","#sun","#light","#sunset","#orange","#shotoniphone"],"timestamp":1591728366,"FullID":"2020-06-09-2327908722791216660","lat":51.566,"long":-0.1338,"location_count":19},{"caption":"Last sunset of 2019 #sunset #horses #view #silhouette #blue #red #purple #sky #x100f","code":"B6xgCfiAjkn","dimensions":{"height":1080,"width":1080},"display_url":"https://scontent-mia3-1.cdninstagram.com/v/t51.2885-15/e35/s1080x1080/81669615_470746453636552_1270966808090606078_n.jpg?_nc_ht=scontent-mia3-1.cdninstagram.com\u0026_nc_cat=104\u0026_nc_ohc=HxbYrLq7FKQAX_8piup\u0026oh=b72e6fbc32c4a37a65fc0e1ae4832451\u0026oe=5E96F970","id":"2211689800799500583","is_video":false,"location":{"has_public_page":true,"id":"857906084","name":"Mey, Highland, United Kingdom","slug":"mey-highland-united-kingdom"},"media_url":"https://scontent-mia3-1.cdninstagram.com/v/t51.2885-15/e35/s1080x1080/81669615_470746453636552_1270966808090606078_n.jpg?_nc_ht=scontent-mia3-1.cdninstagram.com\u0026_nc_cat=104\u0026_nc_ohc=HxbYrLq7FKQAX_8piup\u0026oh=b72e6fbc32c4a37a65fc0e1ae4832451\u0026oe=5E96F970","post_url":"https://www.instagram.com/p/B6xgCfiAjkn","tags":["#sunset","#horses","#view","#silhouette","#blue","#red","#purple","#sky","#x100f"],"timestamp":1577873991,"FullID":"2020-01-01-2211689800799500583","lat":58.636490070834,"long":-3.2301534783333,"location_count":4},{"caption":"Sunset at 15:20 - the shortest day #sunset #beach #sea #firth #mountains #view #landscape #x100f #sand #grass #warm #orange #sky #evening","code":"B6Wl-kfg9b5","dimensions":{"height":1080,"width":1080},"display_url":"https://scontent-mia3-1.cdninstagram.com/v/t51.2885-15/e35/s1080x1080/78956985_2695450013873051_5821877709603938883_n.jpg?_nc_ht=scontent-mia3-1.cdninstagram.com\u0026_nc_cat=111\u0026_nc_ohc=V-_8KWuVAs8AX9TDl1J\u0026oh=db87a6b370e9c05778ec4672ee2f2a07\u0026oe=5EA7F0EA","id":"2204116095156344569","is_video":false,"location":{"has_public_page":true,"id":"1033488271","name":"Redcastle","slug":"redcastle"},"media_url":"https://scontent-mia3-1.cdninstagram.com/v/t51.2885-15/e35/s1080x1080/78956985_2695450013873051_5821877709603938883_n.jpg?_nc_ht=scontent-mia3-1.cdninstagram.com\u0026_nc_cat=111\u0026_nc_ohc=V-_8KWuVAs8AX9TDl1J\u0026oh=db87a6b370e9c05778ec4672ee2f2a07\u0026oe=5EA7F0EA","post_url":"https://www.instagram.com/p/B6Wl-kfg9b5","tags":["#sunset","#beach","#sea","#firth","#mountains","#view","#landscape","#x100f","#sand","#grass","#warm","#orange","#sky","#evening"],"timestamp":1576971135,"FullID":"2019-12-21-2204116095156344569","lat":57.51312,"long":-4.36746,"location_count":37},{"caption":"Osaka 🌇 #sunset #night #evening #clouds #orange #river #view #landscape #x100f #yellow #dramatic","code":"B2lYH8_geaq","dimensions":{"height":1080,"width":1080},"display_url":"https://scontent-lhr3-1.cdninstagram.com/vp/94c6df0cbe4597249866a8ea5af54b97/5E3964F2/t51.2885-15/e35/69010189_2462197107201919_3884212541128599912_n.jpg?_nc_ht=scontent-lhr3-1.cdninstagram.com\u0026_nc_cat=107","id":"2136219697899759274","is_video":false,"location":{"has_public_page":true,"id":"51772","name":"梅田スカイビル（Umeda Sky Building)","slug":"umeda-sky-building"},"media_url":"https://scontent-lhr3-1.cdninstagram.com/vp/94c6df0cbe4597249866a8ea5af54b97/5E3964F2/t51.2885-15/e35/69010189_2462197107201919_3884212541128599912_n.jpg?_nc_ht=scontent-lhr3-1.cdninstagram.com\u0026_nc_cat=107","post_url":"https://www.instagram.com/p/B2lYH8_geaq","tags":["#sunset","#night","#evening","#clouds","#orange","#river","#view","#landscape","#x100f","#yellow","#dramatic"],"timestamp":1568877254,"FullID":"2019-09-19-2136219697899759274","lat":34.705201069342,"long":135.49044897567,"location_count":3},{"caption":"Couples that sky deck together, stay together #silhouette #view #city #colorful #evening #x100f #sunset #couple #lookingdown","code":"B2f9KtNgLXb","dimensions":{"height":1080,"width":1080},"display_url":"https://scontent-lhr3-1.cdninstagram.com/vp/1d81e5a8dccd6d50e0aa815590842728/5E34B751/t51.2885-15/e35/69803423_173585270439904_3367785382356330382_n.jpg?_nc_ht=scontent-lhr3-1.cdninstagram.com\u0026_nc_cat=104","id":"2134693764973770203","is_video":false,"location":{"has_public_page":true,"id":"1176427","name":"ローソン　六本木ヒルズ店","slug":"1176427"},"media_url":"https://scontent-lhr3-1.cdninstagram.com/vp/1d81e5a8dccd6d50e0aa815590842728/5E34B751/t51.2885-15/e35/69803423_173585270439904_3367785382356330382_n.jpg?_nc_ht=scontent-lhr3-1.cdninstagram.com\u0026_nc_cat=104","post_url":"https://www.instagram.com/p/B2f9KtNgLXb","tags":["#silhouette","#view","#city","#colorful","#evening","#x100f","#sunset","#couple","#lookingdown"],"timestamp":1568695348,"FullID":"2019-09-17-2134693764973770203","lat":35.66032139,"long":139.7291497,"location_count":1},{"caption":"Retired tractor has a nice view to wait out its days #tractor #grass #sunset #evening #summer #field #farm #sky #blue #clouds #warm #x100f","code":"By_D9H7Az72","dimensions":{"height":1080,"width":1080},"display_url":"https://scontent-atl3-1.cdninstagram.com/vp/9123fc5af9461e9a5d421b4904442e22/5DAB6FF6/t51.2885-15/e35/61887926_2330917040330572_436622411116581872_n.jpg?_nc_ht=scontent-atl3-1.cdninstagram.com","id":"2071391748147592950","is_video":false,"location":{"has_public_page":true,"id":"246994238","name":"Muir Of Ord, Highland, United Kingdom","slug":"muir-of-ord-highland-united-kingdom"},"media_url":"https://scontent-atl3-1.cdninstagram.com/vp/9123fc5af9461e9a5d421b4904442e22/5DAB6FF6/t51.2885-15/e35/61887926_2330917040330572_436622411116581872_n.jpg?_nc_ht=scontent-atl3-1.cdninstagram.com","post_url":"https://www.instagram.com/p/By_D9H7Az72","tags":["#tractor","#grass","#sunset","#evening","#summer","#field","#farm","#sky","#blue","#clouds","#warm","#x100f"],"timestamp":1561149160,"FullID":"2019-06-21-2071391748147592950","lat":57.5167,"long":-4.45,"location_count":26},{"caption":"Finsbury Square #sunset #reflection #building #bright #sky #dark #architecture #skyscraper #x100f","code":"Bwp2yauANcB","dimensions":{"height":1080,"width":1080},"display_url":"https://scontent-mia3-1.cdninstagram.com/vp/e8e486a4b46eec5da324bc48911c5cab/5D37FDD2/t51.2885-15/e35/57284774_134527510998269_8316883490189507424_n.jpg?_nc_ht=scontent-mia3-1.cdninstagram.com","id":"2029394066281649921","is_video":false,"location":{"has_public_page":true,"id":"221665470","name":"Finsbury Square","slug":"finsbury-square"},"media_url":"https://scontent-mia3-1.cdninstagram.com/vp/e8e486a4b46eec5da324bc48911c5cab/5D37FDD2/t51.2885-15/e35/57284774_134527510998269_8316883490189507424_n.jpg?_nc_ht=scontent-mia3-1.cdninstagram.com","post_url":"https://www.instagram.com/p/Bwp2yauANcB","tags":["#sunset","#reflection","#building","#bright","#sky","#dark","#architecture","#skyscraper","#x100f"],"timestamp":1556142646,"FullID":"2019-04-24-2029394066281649921","lat":51.5209,"long":-0.08649,"location_count":2},{"caption":"Take your pleasure seriously #sunset #reflection #tower #evening #pink #view #teampixel #glass","code":"Bvcq3sig4Fu","dimensions":{"height":1080,"width":1080},"display_url":"https://scontent-atl3-1.cdninstagram.com/vp/00d67cd7fd3a6f2d50d9906d57f9a3a8/5D12B4BE/t51.2885-15/e35/53509737_708667586214595_5557129225891554693_n.jpg?_nc_ht=scontent-atl3-1.cdninstagram.com","id":"2007668079248769390","is_video":false,"location":{"has_public_page":true,"id":"110531","name":"Tottenham Court Road","slug":"tottenham-court-road"},"media_url":"https://scontent-atl3-1.cdninstagram.com/vp/00d67cd7fd3a6f2d50d9906d57f9a3a8/5D12B4BE/t51.2885-15/e35/53509737_708667586214595_5557129225891554693_n.jpg?_nc_ht=scontent-atl3-1.cdninstagram.com","post_url":"https://www.instagram.com/p/Bvcq3sig4Fu","tags":["#sunset","#reflection","#tower","#evening","#pink","#view","#teampixel","#glass"],"timestamp":1553552707,"FullID":"2019-03-25-2007668079248769390","lat":51.5207,"long":-0.1345,"location_count":3},{"caption":"Little potter up Fyrish today #clouds #landscape #view #sunset #winter #hills #mountains #atmospheric #dark #firth #water #x100f","code":"Br5nWTMggcp","dimensions":{"height":1080,"width":1080},"display_url":"https://scontent-atl3-1.cdninstagram.com/vp/6ed22e020118b30df4ff2abba89e68de/5CD83538/t51.2885-15/e35/46841021_2103698789940854_2067759275345707008_n.jpg?_nc_ht=scontent-atl3-1.cdninstagram.com","id":"1943757770440443689","is_video":false,"location":{"has_public_page":true,"id":"255084618","name":"Fyrish Monument","slug":"fyrish-monument"},"media_url":"https://scontent-atl3-1.cdninstagram.com/vp/6ed22e020118b30df4ff2abba89e68de/5CD83538/t51.2885-15/e35/46841021_2103698789940854_2067759275345707008_n.jpg?_nc_ht=scontent-atl3-1.cdninstagram.com","post_url":"https://www.instagram.com/p/Br5nWTMggcp","tags":["#clouds","#landscape","#view","#sunset","#winter","#hills","#mountains","#atmospheric","#dark","#firth","#water","#x100f"],"timestamp":1545934004,"FullID":"2018-12-27-1943757770440443689","lat":57.6956,"long":-4.3375,"location_count":2},{"caption":"Sunset Shheepies #sunset #clouds #sheep #field #herd #farm #winter #evening #x100f","code":"BrdDe8AADPc","dimensions":{"height":1080,"width":1080},"display_url":"https://scontent-atl3-1.cdninstagram.com/vp/d33fc715d2d4c0bb232f7d02ee2caa95/5CD8ED40/t51.2885-15/e35/47582925_325920568229531_7020795546268860416_n.jpg","id":"1935718734987539420","is_video":false,"location":{"has_public_page":true,"id":"1033488271","name":"Redcastle","slug":"redcastle"},"media_url":"https://scontent-atl3-1.cdninstagram.com/vp/d33fc715d2d4c0bb232f7d02ee2caa95/5CD8ED40/t51.2885-15/e35/47582925_325920568229531_7020795546268860416_n.jpg","post_url":"https://www.instagram.com/p/BrdDe8AADPc","tags":["#sunset","#clouds","#sheep","#field","#herd","#farm","#winter","#evening","#x100f"],"timestamp":1544975676,"FullID":"2018-12-16-1935718734987539420","lat":57.51312,"long":-4.36746,"location_count":37},{"caption":"But you\u0026#x27;ve got an unquenchable thirst for New York #city #shotonmoment #teampixel #shotonpixel #view #cityscape #evening #sunset #orange #sky #clear #cold #clouds #warm #juicy","code":"BpP6GRmgpAE","dimensions":{"height":1080,"width":1080},"display_url":"https://scontent-atl3-1.cdninstagram.com/vp/5fba47f32f46108211ddbfbda00f40e3/5C4785AE/t51.2885-15/e35/43779414_988372658014546_9092319729816698880_n.jpg","id":"1895989486060474372","is_video":false,"location":{"has_public_page":true,"id":"221447018442743","name":"Top of the Rock","slug":"top-of-the-rock"},"media_url":"https://scontent-atl3-1.cdninstagram.com/vp/5fba47f32f46108211ddbfbda00f40e3/5C4785AE/t51.2885-15/e35/43779414_988372658014546_9092319729816698880_n.jpg","post_url":"https://www.instagram.com/p/BpP6GRmgpAE","tags":["#x27","#city","#shotonmoment","#teampixel","#shotonpixel","#view","#cityscape","#evening","#sunset","#orange","#sky","#clear","#cold","#clouds","#warm","#juicy"],"timestamp":1540239581,"FullID":"2018-10-22-1895989486060474372","lat":40.7593504119,"long":-73.9803604087,"location_count":4},{"caption":"We\u0026#x27;ve come a long long way together #friends #bff #view #city #sunset #hug #hair #evening #cold #jacket #x100f","code":"BpPxw0lABtE","dimensions":{"height":1080,"width":1080},"display_url":"https://scontent-atl3-1.cdninstagram.com/vp/c572566e8fc23f54ccbe6999105c6cb3/5C595F16/t51.2885-15/e35/43915119_2226543937576382_7852762678945644544_n.jpg","id":"1895952827415534404","is_video":false,"location":{"has_public_page":true,"id":"221447018442743","name":"Top of the Rock","slug":"top-of-the-rock"},"media_url":"https://scontent-atl3-1.cdninstagram.com/vp/c572566e8fc23f54ccbe6999105c6cb3/5C595F16/t51.2885-15/e35/43915119_2226543937576382_7852762678945644544_n.jpg","post_url":"https://www.instagram.com/p/BpPxw0lABtE","tags":["#x27","#friends","#bff","#view","#city","#sunset","#hug","#hair","#evening","#cold","#jacket","#x100f"],"timestamp":1540235211,"FullID":"2018-10-22-1895952827415534404","lat":40.7593504119,"long":-73.9803604087,"location_count":4},{"caption":"Goodbye Washington #night #monument #dusk #sunset #orange #blue #sky #x100f #horizon #silhouette","code":"BpFYbMKg10s","dimensions":{"height":1080,"width":1080},"display_url":"https://scontent-iad3-1.cdninstagram.com/vp/8970f73261267740eb2630434c782978/5C4FE63B/t51.2885-15/e35/42947856_2301006483256611_2077613489395859456_n.jpg","id":"1893026639982583084","is_video":false,"location":{"has_public_page":true,"id":"1191441824276882","name":"The White House","slug":"the-white-house"},"media_url":"https://scontent-iad3-1.cdninstagram.com/vp/8970f73261267740eb2630434c782978/5C4FE63B/t51.2885-15/e35/42947856_2301006483256611_2077613489395859456_n.jpg","post_url":"https://www.instagram.com/p/BpFYbMKg10s","tags":["#night","#monument","#dusk","#sunset","#orange","#blue","#sky","#x100f","#horizon","#silhouette"],"timestamp":1539886382,"FullID":"2018-10-18-1893026639982583084","lat":38.8968446741,"long":-77.0366048813,"location_count":1},{"caption":"Nice night for it. #kayak #seascape #landscape #evening #view #reflection #sunset #dusk #x100f #canoe","code":"Bo90FptAwyB","dimensions":{"height":1080,"width":1080},"display_url":"https://scontent-atl3-1.cdninstagram.com/vp/9a4589ab00ed19869864d36ef054e83b/5C53E038/t51.2885-15/e35/42542348_1772014629587335_3838685449535094784_n.jpg","id":"1890896505360026753","is_video":false,"location":{"has_public_page":true,"id":"244597203","name":"Ullapool","slug":"ullapool"},"media_url":"https://scontent-atl3-1.cdninstagram.com/vp/9a4589ab00ed19869864d36ef054e83b/5C53E038/t51.2885-15/e35/42542348_1772014629587335_3838685449535094784_n.jpg","post_url":"https://www.instagram.com/p/Bo90FptAwyB","tags":["#kayak","#seascape","#landscape","#evening","#view","#reflection","#sunset","#dusk","#x100f","#canoe"],"timestamp":1539632450,"FullID":"2018-10-15-1890896505360026753","lat":57.8986111111,"long":-5.1602777778,"location_count":8},{"caption":"This is where I grew up #sunset #clouds #orange #yellow #evening #dusk #rain #reflection #view #night #purple #x100f","code":"Bo4IBkRgj5M","dimensions":{"height":1080,"width":1080},"display_url":"https://scontent-mia3-2.cdninstagram.com/vp/58cf5fafee158eb83bbb4fddf2a643a3/5C5E481E/t51.2885-15/e35/42471689_1973564166073047_5805984842826907648_n.jpg","id":"1889295335721942604","is_video":false,"location":{"has_public_page":true,"id":"246994238","name":"Muir Of Ord, Highland, United Kingdom","slug":"muir-of-ord-highland-united-kingdom"},"media_url":"https://scontent-mia3-2.cdninstagram.com/vp/58cf5fafee158eb83bbb4fddf2a643a3/5C5E481E/t51.2885-15/e35/42471689_1973564166073047_5805984842826907648_n.jpg","post_url":"https://www.instagram.com/p/Bo4IBkRgj5M","tags":["#sunset","#clouds","#orange","#yellow","#evening","#dusk","#rain","#reflection","#view","#night","#purple","#x100f"],"timestamp":1539441576,"FullID":"2018-10-13-1889295335721942604","lat":57.5167,"long":-4.45,"location_count":26},{"caption":"Wast water #lake #mountain #landscape #view #nature #sunset #evening #clouds #atmosphere #sun #glow #mountain #hill #hike #walk #x100f","code":"Boc0qxbAQj2","dimensions":{"height":1080,"width":1080},"display_url":"https://instagram.flis3-1.fna.fbcdn.net/vp/a2c18f2f021be9477261c53adb78acd6/5C43F4E5/t51.2885-15/e35/41698861_329181331166023_7074153187707453440_n.jpg","id":"1881610382037027062","is_video":false,"location":{"has_public_page":true,"id":"863555074","name":"Wast Water","slug":"wast-water"},"media_url":"https://instagram.flis3-1.fna.fbcdn.net/vp/a2c18f2f021be9477261c53adb78acd6/5C43F4E5/t51.2885-15/e35/41698861_329181331166023_7074153187707453440_n.jpg","post_url":"https://www.instagram.com/p/Boc0qxbAQj2","tags":["#lake","#mountain","#landscape","#view","#nature","#sunset","#evening","#clouds","#atmosphere","#sun","#glow","#hill","#hike","#walk","#x100f"],"timestamp":1538525458,"FullID":"2018-10-03-1881610382037027062","lat":54.4416666667,"long":-3.2916666667,"location_count":3},{"caption":"Jacob #jacobsladder #sun #sunset #plane #x100f","code":"BmLnMhmgKYG","dimensions":{"height":1080,"width":1080},"display_url":"https://scontent-lax3-2.cdninstagram.com/vp/8f22240f3b3f68e3780f9c921f12a88f/5C1316D4/t51.2885-15/e35/37762138_243209582985615_665685038565687296_n.jpg","id":"1840737257238078982","is_video":false,"location":{"has_public_page":true,"id":"49143886","name":"Putney","slug":"putney"},"media_url":"https://scontent-lax3-2.cdninstagram.com/vp/8f22240f3b3f68e3780f9c921f12a88f/5C1316D4/t51.2885-15/e35/37762138_243209582985615_665685038565687296_n.jpg","post_url":"https://www.instagram.com/p/BmLnMhmgKYG","tags":["#jacobsladder","#sun","#sunset","#plane","#x100f"],"timestamp":1533653002,"FullID":"2018-08-07-1840737257238078982","lat":51.4611780318,"long":-0.2166802887,"location_count":46},{"caption":"You're a bit sweaty\n.\n.\n.\n#couple #evening #sunset #x100f","code":"BlTxZDjA3BH","dimensions":{"height":1080,"width":1080},"display_url":"https://scontent-lax3-2.cdninstagram.com/vp/9ba5456b8a27f87c7caed3db3307be0e/5BE54F64/t51.2885-15/e35/36789547_564158097368411_1199979275130765312_n.jpg","id":"1825019500089798727","is_video":false,"location":{"has_public_page":true,"id":"216718485","name":"Oxo Tower Wharf","slug":"oxo-tower-wharf"},"media_url":"https://scontent-lax3-2.cdninstagram.com/vp/9ba5456b8a27f87c7caed3db3307be0e/5BE54F64/t51.2885-15/e35/36789547_564158097368411_1199979275130765312_n.jpg","post_url":"https://www.instagram.com/p/BlTxZDjA3BH","tags":["#couple","#evening","#sunset","#x100f"],"timestamp":1531779299,"FullID":"2018-07-16-1825019500089798727","lat":51.508389017,"long":-0.1084899804,"location_count":6},{"caption":"Blackbird\n.\n.\n.\n#silhouette #dark #sunset #evening #nofilter #x100f #clouds #sky #cloud","code":"Bk3gAKiA60V","dimensions":{"height":1080,"width":1080},"display_url":"https://scontent-lax3-2.cdninstagram.com/vp/190293b7ea21cde509511c5f0319b60c/5BE27B47/t51.2885-15/e35/36049098_189534978386721_7847156492493914112_n.jpg?efg=eyJ1cmxnZW4iOiJ1cmxnZW5fZnJvbV9pZyJ9","id":"1817061723463724309","is_video":false,"location":{"has_public_page":true,"id":"49143886","name":"Putney","slug":"putney"},"media_url":"https://scontent-lax3-2.cdninstagram.com/vp/190293b7ea21cde509511c5f0319b60c/5BE27B47/t51.2885-15/e35/36049098_189534978386721_7847156492493914112_n.jpg?efg=eyJ1cmxnZW4iOiJ1cmxnZW5fZnJvbV9pZyJ9","post_url":"https://www.instagram.com/p/Bk3gAKiA60V","tags":["#silhouette","#dark","#sunset","#evening","#nofilter","#x100f","#clouds","#sky","#cloud"],"timestamp":1530830658,"FullID":"2018-07-05-1817061723463724309","lat":51.4611780318,"long":-0.2166802887,"location_count":46},{"caption":"Needing something a bit wider, there's a converter lens for that. As they say...\n.\n.\n.\n#architecture #cranes #construction #lookingup #crane #geometric #reflection #sunset #sun #evening #sky #nofilter #x100f","code":"Bk3A_bRgSxu","dimensions":{"height":1080,"width":1080},"display_url":"https://scontent-lax3-2.cdninstagram.com/vp/22d8ec2e130abf0ebb17e7a2f466ec55/5BDDFFCF/t51.2885-15/e35/36578730_1400334630067189_4272732224538804224_n.jpg?efg=eyJ1cmxnZW4iOiJ1cmxnZW5fZnJvbV9pZyJ9","id":"1816925333279026286","is_video":false,"location":{"has_public_page":true,"id":"502239540","name":"London Waterloo station","slug":"london-waterloo-station"},"media_url":"https://scontent-lax3-2.cdninstagram.com/vp/22d8ec2e130abf0ebb17e7a2f466ec55/5BDDFFCF/t51.2885-15/e35/36578730_1400334630067189_4272732224538804224_n.jpg?efg=eyJ1cmxnZW4iOiJ1cmxnZW5fZnJvbV9pZyJ9","post_url":"https://www.instagram.com/p/Bk3A_bRgSxu","tags":["#architecture","#cranes","#construction","#lookingup","#crane","#geometric","#reflection","#sunset","#sun","#evening","#sky","#nofilter","#x100f"],"timestamp":1530814399,"FullID":"2018-07-05-1816925333279026286","lat":51.5031,"long":-0.1132,"location_count":10},{"caption":"Until next time. #illbeback\n.\n.\n.\n#sleeper #train #sunset #rails #train #landscape #view #west #orange #glow #purple #dark #night #evening #summer #travel #holiday #teampixel #shotonpixel #nofilter #snapseed #picoftheday #picofthenight","code":"BkdqBszAyUl","dimensions":{"height":1080,"width":1080},"display_url":"https://scontent-lax3-2.cdninstagram.com/vp/83226efe762442d2193abd457e2c597f/5BAD2F96/t51.2885-15/e35/35353134_470847810041203_8868945339814510592_n.jpg","id":"1809787460046234917","is_video":false,"location":{"has_public_page":true,"id":"228514641","name":"Pass of Drumochter","slug":"pass-of-drumochter"},"media_url":"https://scontent-lax3-2.cdninstagram.com/vp/83226efe762442d2193abd457e2c597f/5BAD2F96/t51.2885-15/e35/35353134_470847810041203_8868945339814510592_n.jpg","post_url":"https://www.instagram.com/p/BkdqBszAyUl","tags":["#illbeback","#sleeper","#train","#sunset","#rails","#landscape","#view","#west","#orange","#glow","#purple","#dark","#night","#evening","#summer","#travel","#holiday","#teampixel","#shotonpixel","#nofilter","#snapseed","#picoftheday","#picofthenight"],"timestamp":1529963499,"FullID":"2018-06-25-1809787460046234917","lat":56.8596388889,"long":-4.2485611111,"location_count":2},{"caption":"This isnt some wonky filter. The path is actually covered in purple poster paint, at a glance it looks like a lovely pink sunset though.\n.\n.\n.\n#pink #sunset #paint #purple #nature #park #trees #summer #walks #potter #trail #track #wander #nofilter #picoftheday #instagood","code":"BkGc0vXF5AU","dimensions":{"height":1080,"width":1080},"display_url":"https://scontent-lax3-2.cdninstagram.com/vp/7f155d7ca4fe1b23e32c79bad1bcc82c/5BADB818/t51.2885-15/e35/35520444_225849624859683_5788560139032199168_n.jpg","id":"1803255470376849428","is_video":false,"location":{"has_public_page":true,"id":"2410312","name":"Bishops Meadow","slug":"bishops-meadow"},"media_url":"https://scontent-lax3-2.cdninstagram.com/vp/7f155d7ca4fe1b23e32c79bad1bcc82c/5BADB818/t51.2885-15/e35/35520444_225849624859683_5788560139032199168_n.jpg","post_url":"https://www.instagram.com/p/BkGc0vXF5AU","tags":["#pink","#sunset","#paint","#purple","#nature","#park","#trees","#summer","#walks","#potter","#trail","#track","#wander","#nofilter","#picoftheday","#instagood"],"timestamp":1529184825,"FullID":"2018-06-16-1803255470376849428","lat":52.0505832386,"long":-2.714924562,"location_count":3},{"caption":"Home time. Sitting at the back of the plane to make avoid the wings in my photos. Would have gone to the front but it's twice the price. .\n.\n.\n#watchtower #airtrafficcontrol #lights #flare #airport #travel #trip #holiday #teampixel #planewindow #sunset #sun #pinksky #orange #pink #lines #holiday #nofilter","code":"BjiYzVwlAYd","dimensions":{"height":1080,"width":1080},"display_url":"https://scontent-lax3-2.cdninstagram.com/vp/2bffd7e29b3099284247ab2a8b0f5dc7/5BA67A2E/t51.2885-15/e35/33908137_199460874037155_7384678189336887296_n.jpg","id":"1793104682820044317","is_video":false,"location":{"has_public_page":true,"id":"215178522","name":"Aeroporto de Faro","slug":"aeroporto-de-faro"},"media_url":"https://scontent-lax3-2.cdninstagram.com/vp/2bffd7e29b3099284247ab2a8b0f5dc7/5BA67A2E/t51.2885-15/e35/33908137_199460874037155_7384678189336887296_n.jpg","post_url":"https://www.instagram.com/p/BjiYzVwlAYd","tags":["#watchtower","#airtrafficcontrol","#lights","#flare","#airport","#travel","#trip","#holiday","#teampixel","#planewindow","#sunset","#sun","#pinksky","#orange","#pink","#lines","#nofilter"],"timestamp":1527974757,"FullID":"2018-06-02-1793104682820044317","lat":37.0202276444,"long":-7.9679406019,"location_count":3},{"caption":"We will shortly be beginning our decent into Faro. Best flight I've had in a while.\n.\n.\n.\n#plane #sunset #holiday #view #wing #nofilter #teampixel","code":"BjQMRKNl80u","dimensions":{"height":1080,"width":1080},"display_url":"https://scontent-lax3-2.cdninstagram.com/vp/f3f62d513e741aa578c5bdadbf748024/5B9DBEB9/t51.2885-15/e35/31449069_834481820083225_6984254265162203136_n.jpg","id":"1787983007820795182","is_video":false,"location":{"has_public_page":true,"id":"215178522","name":"Aeroporto de Faro","slug":"aeroporto-de-faro"},"media_url":"https://scontent-lax3-2.cdninstagram.com/vp/f3f62d513e741aa578c5bdadbf748024/5B9DBEB9/t51.2885-15/e35/31449069_834481820083225_6984254265162203136_n.jpg","post_url":"https://www.instagram.com/p/BjQMRKNl80u","tags":["#plane","#sunset","#holiday","#view","#wing","#nofilter","#teampixel"],"timestamp":1527364205,"FullID":"2018-05-26-1787983007820795182","lat":37.0202276444,"long":-7.9679406019,"location_count":3},{"caption":"This is another image generated from stacked video frames using my new 'stackr' app. Read about stackr on my blog. More examples to follow.\n.\n.\n.\n#stackmode #imagestack #nophotoshop #thames #sunset #reflection #river #clouds #hdr #shotonpixel #teampixel #nofilter #nofilterneeded  #longexposure","code":"BiA0zgpl5Ph","dimensions":{"height":1080,"width":1080},"display_url":"https://scontent-lax3-2.cdninstagram.com/vp/cfe6c15684abfebbe081ceaa3b3e25e7/5B60625A/t51.2885-15/e35/30603726_168365770511481_1836939701269823488_n.jpg","id":"1765643292098663393","is_video":false,"location":{"has_public_page":true,"id":"213096864","name":"Millennium Bridge, London","slug":"millennium-bridge-london"},"media_url":"https://scontent-lax3-2.cdninstagram.com/vp/cfe6c15684abfebbe081ceaa3b3e25e7/5B60625A/t51.2885-15/e35/30603726_168365770511481_1836939701269823488_n.jpg","post_url":"https://www.instagram.com/p/BiA0zgpl5Ph","tags":["#stackmode","#imagestack","#nophotoshop","#thames","#sunset","#reflection","#river","#clouds","#hdr","#shotonpixel","#teampixel","#nofilter","#nofilterneeded","#longexposure"],"timestamp":1524701104,"FullID":"2018-04-26-1765643292098663393","lat":51.510173,"long":-0.098438,"location_count":2},{"caption":"The London eye is surrounded by so much shite it's hard to get a good photo.\n.\n.\n.\n#londoneye #trees #sunset #shotonmoment #teampixel #shotonpixel #nofilter #nofilterneeded #tree #sunrise #forest #londonstyle #leaves #sunsets #treestagram #woods #treescape #sunset_madness #sunset_pics #skyline #evening #horizon #londoncity #water #dusk #londres #sunshine #londoner #landscapes #light","code":"BhuZz7ohNn5","dimensions":{"height":1080,"width":1080},"display_url":"https://scontent-lax3-2.cdninstagram.com/vp/2d79fd676a50f4772834d868cf1504e9/5B58C40B/t51.2885-15/e35/30078424_256790084866471_3706924309684420608_n.jpg","id":"1760458024235096569","is_video":false,"location":{"has_public_page":true,"id":"8562373","name":"The Official London Eye","slug":"the-official-london-eye"},"media_url":"https://scontent-lax3-2.cdninstagram.com/vp/2d79fd676a50f4772834d868cf1504e9/5B58C40B/t51.2885-15/e35/30078424_256790084866471_3706924309684420608_n.jpg","post_url":"https://www.instagram.com/p/BhuZz7ohNn5","tags":["#londoneye","#trees","#sunset","#shotonmoment","#teampixel","#shotonpixel","#nofilter","#nofilterneeded","#tree","#sunrise","#forest","#londonstyle","#leaves","#sunsets","#treestagram","#woods","#treescape","#sunset_madness","#sunset_pics","#skyline","#evening","#horizon","#londoncity","#water","#dusk","#londres","#sunshine","#londoner","#landscapes","#light"],"timestamp":1524082972,"FullID":"2018-04-18-1760458024235096569","lat":51.5033647803,"long":-0.1193473491,"location_count":2},{"caption":"Will the sun come back tomorrow?\n.\n.\n.\n#sunset #view #thames #river #orange #sky #shotonmoment #teampixel #shotonpixel #nofilter #scenery #nofilterneeded #landscapes #riverthames #all_sunsets #bridge #water #sunsets #horizon #scenicsunset #riverside #cloud #londoncity #sunrays #bluesky #instasunsets  #sunset_madness","code":"BhuP9LLBf0g","dimensions":{"height":1080,"width":1080},"display_url":"https://scontent-lax3-2.cdninstagram.com/vp/c31a0fd4d733dc8bd3825b3623bb758c/5B5664B4/t51.2885-15/e35/30079752_1843485405716280_4323225921654882304_n.jpg","id":"1760414678930292000","is_video":false,"location":{"has_public_page":true,"id":"25619","name":"South Bank London","slug":"south-bank-london"},"media_url":"https://scontent-lax3-2.cdninstagram.com/vp/c31a0fd4d733dc8bd3825b3623bb758c/5B5664B4/t51.2885-15/e35/30079752_1843485405716280_4323225921654882304_n.jpg","post_url":"https://www.instagram.com/p/BhuP9LLBf0g","tags":["#sunset","#view","#thames","#river","#orange","#sky","#shotonmoment","#teampixel","#shotonpixel","#nofilter","#scenery","#nofilterneeded","#landscapes","#riverthames","#all_sunsets","#bridge","#water","#sunsets","#horizon","#scenicsunset","#riverside","#cloud","#londoncity","#sunrays","#bluesky","#instasunsets","#sunset_madness"],"timestamp":1524077804,"FullID":"2018-04-18-1760414678930292000","lat":51.5059584676,"long":-0.1174122265,"location_count":9},{"caption":"Oops, first missed post in 2017 - 29 mins late .\n.\n.\n#sunset #night #evening #cool #summer #uist #scotland #sky #atmosphere #Landscapephotography #landscapelover #landscape_captures #landscapes #landscape_photography #landscapecaptures #landscapestyles_gf #landscape_specialist  #landscapephotomag #ig_landscape #ig_masterpiece  #discoverearth #exploretheglobe #earthfocus #ourplanetdaily #natgeo #nationalgeographic #awesome_earthpix #nofilter","code":"BXwKVNFl0KV","dimensions":{"height":1080,"width":1080},"display_url":"https://scontent-lht6-1.cdninstagram.com/vp/24e25ab25790c687102ce5ccddbd16d4/5B1EFA70/t51.2885-15/e35/20759161_280923229053633_3676845232076357632_n.jpg","id":"1580808906833609365","is_video":false,"location":{"has_public_page":true,"id":"1029615837","name":"South Uist","slug":"south-uist"},"media_url":"https://scontent-lht6-1.cdninstagram.com/vp/24e25ab25790c687102ce5ccddbd16d4/5B1EFA70/t51.2885-15/e35/20759161_280923229053633_3676845232076357632_n.jpg","post_url":"https://www.instagram.com/p/BXwKVNFl0KV","tags":["#sunset","#night","#evening","#cool","#summer","#uist","#scotland","#sky","#atmosphere","#Landscapephotography","#landscapelover","#landscape_captures","#landscapes","#landscape_photography","#landscapecaptures","#landscapestyles_gf","#landscape_specialist","#landscapephotomag","#ig_landscape","#ig_masterpiece","#discoverearth","#exploretheglobe","#earthfocus","#ourplanetdaily","#natgeo","#nationalgeographic","#awesome_earthpix","#nofilter"],"timestamp":1502667128,"FullID":"2017-08-14-1580808906833609365","lat":57.2666666667,"long":-7.3166666667,"location_count":68},{"caption":"Kelp or something\n.\n.\n.\n#beach #landscape #seaweed #seascape #view #reflection #view #evening #sunset #Landscapephotography #landscapelover #landscape_captures #landscapes #landscape_photography #landscapecaptures #landscapestyles_gf #landscape_specialist  #landscapephotomag #ig_landscape #ig_masterpiece  #discoverearth #exploretheglobe #earthfocus #ourplanetdaily #natgeo #nationalgeographic #awesome_earthpix","code":"BXqtpdvADma","dimensions":{"height":1078,"width":1080},"display_url":"https://scontent-lht6-1.cdninstagram.com/vp/83f328c60e7efc36a351d444381eb801/5B0DFE94/t51.2885-15/e35/20688339_302444383557529_8488561157517344768_n.jpg","id":"1579275380865382810","is_video":false,"location":{"has_public_page":true,"id":"1029615837","name":"South Uist","slug":"south-uist"},"media_url":"https://scontent-lht6-1.cdninstagram.com/vp/83f328c60e7efc36a351d444381eb801/5B0DFE94/t51.2885-15/e35/20688339_302444383557529_8488561157517344768_n.jpg","post_url":"https://www.instagram.com/p/BXqtpdvADma","tags":["#beach","#landscape","#seaweed","#seascape","#view","#reflection","#evening","#sunset","#Landscapephotography","#landscapelover","#landscape_captures","#landscapes","#landscape_photography","#landscapecaptures","#landscapestyles_gf","#landscape_specialist","#landscapephotomag","#ig_landscape","#ig_masterpiece","#discoverearth","#exploretheglobe","#earthfocus","#ourplanetdaily","#natgeo","#nationalgeographic","#awesome_earthpix"],"timestamp":1502484317,"FullID":"2017-08-11-1579275380865382810","lat":57.2666666667,"long":-7.3166666667,"location_count":68},{"caption":"Bog Cotton\n.\n.\n.\n#landscape #bogcotton #view #sunset #clouds #sky #sun #orange #Landscapephotography #landscapelover #landscape_captures #landscapes #landscape_photography #landscapecaptures #landscapestyles_gf #landscape_specialist  #landscapephotomag #ig_landscape #ig_masterpiece  #discoverearth #exploretheglobe #earthfocus #ourplanetdaily #natgeo #nationalgeographic #awesome_earthpix #nofilter #nofilterneeded","code":"BXgL6j-gi5s","dimensions":{"height":1078,"width":1080},"display_url":"https://scontent-lht6-1.cdninstagram.com/vp/1950888218765c54e63696c674f76696/5B2AE7B0/t51.2885-15/e35/20686411_109505303084507_1784065299486605312_n.jpg","id":"1576312272450629228","is_video":false,"location":{"has_public_page":true,"id":"360575353","name":"Beinn Mhòr (South Uist)","slug":"beinn-mhor-south-uist"},"media_url":"https://scontent-lht6-1.cdninstagram.com/vp/1950888218765c54e63696c674f76696/5B2AE7B0/t51.2885-15/e35/20686411_109505303084507_1784065299486605312_n.jpg","post_url":"https://www.instagram.com/p/BXgL6j-gi5s","tags":["#landscape","#bogcotton","#view","#sunset","#clouds","#sky","#sun","#orange","#Landscapephotography","#landscapelover","#landscape_captures","#landscapes","#landscape_photography","#landscapecaptures","#landscapestyles_gf","#landscape_specialist","#landscapephotomag","#ig_landscape","#ig_masterpiece","#discoverearth","#exploretheglobe","#earthfocus","#ourplanetdaily","#natgeo","#nationalgeographic","#awesome_earthpix","#nofilter","#nofilterneeded"],"timestamp":1502131087,"FullID":"2017-08-07-1576312272450629228","lat":57.2584,"long":-7.29491,"location_count":3},{"caption":"I have so many photos of this evening. Best. Sunset. Ever.\n.\n.\n.\n#sunset #uist #scotland #night #evening #view #Landscapephotography #landscapelover #landscape_captures #landscapes #landscape_photography #landscapecaptures #landscapestyles_gf #landscape_specialist  #landscapephotomag #ig_landscape #ig_masterpiece  #discoverearth #exploretheglobe #earthfocus #ourplanetdaily #natgeo #nationalgeographic #awesome_earthpix","code":"BXBPXZel1VC","dimensions":{"height":1080,"width":1080},"display_url":"https://scontent-lht6-1.cdninstagram.com/vp/e6d8b2e24e49744fa65ebfe3a3638c85/5B15139E/t51.2885-15/e35/20225617_172767169934171_1280910778408370176_n.jpg","id":"1567601723904054594","is_video":false,"location":{"has_public_page":true,"id":"1029615837","name":"South Uist","slug":"south-uist"},"media_url":"https://scontent-lht6-1.cdninstagram.com/vp/e6d8b2e24e49744fa65ebfe3a3638c85/5B15139E/t51.2885-15/e35/20225617_172767169934171_1280910778408370176_n.jpg","post_url":"https://www.instagram.com/p/BXBPXZel1VC","tags":["#sunset","#uist","#scotland","#night","#evening","#view","#Landscapephotography","#landscapelover","#landscape_captures","#landscapes","#landscape_photography","#landscapecaptures","#landscapestyles_gf","#landscape_specialist","#landscapephotomag","#ig_landscape","#ig_masterpiece","#discoverearth","#exploretheglobe","#earthfocus","#ourplanetdaily","#natgeo","#nationalgeographic","#awesome_earthpix"],"timestamp":1501092709,"FullID":"2017-07-26-1567601723904054594","lat":57.2666666667,"long":-7.3166666667,"location_count":68},{"caption":"Climbing Beinn Mhor late in the day\n.\n.\n.\n#sunset #hiking #uist #view #scotland #reflection #sunbeams #ocean #atlantic #Landscapephotography #landscapelover #landscape_captures #landscapes #landscape_photography #landscapecaptures #landscapestyles_gf #landscape_specialist  #landscapephotomag #ig_landscape #ig_masterpiece  #discoverearth #exploretheglobe #earthfocus #ourplanetdaily #natgeo #nationalgeographic #awesome_earthpix","code":"BWlTElHAsrU","dimensions":{"height":1078,"width":1080},"display_url":"https://scontent-lht6-1.cdninstagram.com/vp/67fa5d75313f37b6bcf4afca93996ec9/5B2B0CF2/t51.2885-15/e35/19984987_127003531238628_4640294486348398592_n.jpg","id":"1559736723561433812","is_video":false,"location":{"has_public_page":true,"id":"1029615837","name":"South Uist","slug":"south-uist"},"media_url":"https://scontent-lht6-1.cdninstagram.com/vp/67fa5d75313f37b6bcf4afca93996ec9/5B2B0CF2/t51.2885-15/e35/19984987_127003531238628_4640294486348398592_n.jpg","post_url":"https://www.instagram.com/p/BWlTElHAsrU","tags":["#sunset","#hiking","#uist","#view","#scotland","#reflection","#sunbeams","#ocean","#atlantic","#Landscapephotography","#landscapelover","#landscape_captures","#landscapes","#landscape_photography","#landscapecaptures","#landscapestyles_gf","#landscape_specialist","#landscapephotomag","#ig_landscape","#ig_masterpiece","#discoverearth","#exploretheglobe","#earthfocus","#ourplanetdaily","#natgeo","#nationalgeographic","#awesome_earthpix"],"timestamp":1500155128,"FullID":"2017-07-15-1559736723561433812","lat":57.2666666667,"long":-7.3166666667,"location_count":68},{"caption":"Uist Meadow\n.\n.\n.\n#sunset #meadow #view #beauty #flowers #scotland #uist #yellow #evening #agameoftones #ig_masterpiece #ig_exquisite #ig_shotz #global_hotshotz #superhubs #main_vision #master_shots #exclusive_shots #hubs_united #jaw_dropping_shotz #worldshotz #theworldshotz #pixel_ig #photographyislifee #photographyislife #photographysouls #photographyeveryday #photographylover","code":"BWdKYc1gpll","dimensions":{"height":1080,"width":1080},"display_url":"https://scontent-lht6-1.cdninstagram.com/vp/aac80fdae2dbfe1b2430144c23d3bfab/5B4E0761/t51.2885-15/e35/19955364_1931680633758753_8777651399006617600_n.jpg","id":"1557446706835134821","is_video":false,"location":{"has_public_page":true,"id":"1029615837","name":"South Uist","slug":"south-uist"},"media_url":"https://scontent-lht6-1.cdninstagram.com/vp/aac80fdae2dbfe1b2430144c23d3bfab/5B4E0761/t51.2885-15/e35/19955364_1931680633758753_8777651399006617600_n.jpg","post_url":"https://www.instagram.com/p/BWdKYc1gpll","tags":["#sunset","#meadow","#view","#beauty","#flowers","#scotland","#uist","#yellow","#evening","#agameoftones","#ig_masterpiece","#ig_exquisite","#ig_shotz","#global_hotshotz","#superhubs","#main_vision","#master_shots","#exclusive_shots","#hubs_united","#jaw_dropping_shotz","#worldshotz","#theworldshotz","#pixel_ig","#photographyislifee","#photographyislife","#photographysouls","#photographyeveryday","#photographylover"],"timestamp":1499882137,"FullID":"2017-07-12-1557446706835134821","lat":57.2666666667,"long":-7.3166666667,"location_count":68},{"caption":"Track south\n.\n.\n.\n#track #sunset #view #green #sun #road #scotland #uist #landscapelover #landscape_captures #landscapes #landscape_photography #landscapecaptures #landscapestyles_gf #landscape_specialist  #landscapephotomag #ig_landscape #ig_masterpiece  #discoverearth #exploretheglobe #earthfocus #ourplanetdaily #natgeo #nationalgeographic #awesome_earthpix","code":"BWYHM64lzIh","dimensions":{"height":1078,"width":1080},"display_url":"https://scontent-lht6-1.cdninstagram.com/vp/d81685bb81a6cd4c5fa44adbcde3c2fb/5B12CBFF/t51.2885-15/e35/19984593_133349473917704_321722591255461888_n.jpg","id":"1556025345442263585","is_video":false,"location":{"has_public_page":true,"id":"1029615837","name":"South Uist","slug":"south-uist"},"media_url":"https://scontent-lht6-1.cdninstagram.com/vp/d81685bb81a6cd4c5fa44adbcde3c2fb/5B12CBFF/t51.2885-15/e35/19984593_133349473917704_321722591255461888_n.jpg","post_url":"https://www.instagram.com/p/BWYHM64lzIh","tags":["#track","#sunset","#view","#green","#sun","#road","#scotland","#uist","#landscapelover","#landscape_captures","#landscapes","#landscape_photography","#landscapecaptures","#landscapestyles_gf","#landscape_specialist","#landscapephotomag","#ig_landscape","#ig_masterpiece","#discoverearth","#exploretheglobe","#earthfocus","#ourplanetdaily","#natgeo","#nationalgeographic","#awesome_earthpix"],"timestamp":1499712697,"FullID":"2017-07-10-1556025345442263585","lat":57.2666666667,"long":-7.3166666667,"location_count":68},{"caption":"Grazing into the night\n.\n.\n.\n#uist #Scotland #clouds #sunset #orange #nofilter #nofilterneeded #landscapelover #landscape_captures #landscapes #landscape_photography #landscapecaptures #landscapestyles_gf #landscape_specialist  #landscapephotomag #ig_landscape #ig_masterpiece  #discoverearth #exploretheglobe #earthfocus #ourplanetdaily #natgeo #nationalgeographic #awesome_earthpix","code":"BWSNfUolN1f","dimensions":{"height":1080,"width":1080},"display_url":"https://scontent-lht6-1.cdninstagram.com/vp/4621b3660c111301a010cf3536367c0a/5B155DC6/t51.2885-15/e35/19761314_1253289051464711_8783877061476352000_n.jpg","id":"1554364148460346719","is_video":false,"location":{"has_public_page":true,"id":"1029615837","name":"South Uist","slug":"south-uist"},"media_url":"https://scontent-lht6-1.cdninstagram.com/vp/4621b3660c111301a010cf3536367c0a/5B155DC6/t51.2885-15/e35/19761314_1253289051464711_8783877061476352000_n.jpg","post_url":"https://www.instagram.com/p/BWSNfUolN1f","tags":["#uist","#Scotland","#clouds","#sunset","#orange","#nofilter","#nofilterneeded","#landscapelover","#landscape_captures","#landscapes","#landscape_photography","#landscapecaptures","#landscapestyles_gf","#landscape_specialist","#landscapephotomag","#ig_landscape","#ig_masterpiece","#discoverearth","#exploretheglobe","#earthfocus","#ourplanetdaily","#natgeo","#nationalgeographic","#awesome_earthpix"],"timestamp":1499514667,"FullID":"2017-07-08-1554364148460346719","lat":57.2666666667,"long":-7.3166666667,"location_count":68},{"caption":"Over the sea to Lochboisdale\n.\n.\n.\n#calmac #ferry #sea #westernisles #scotland #holiday #evening #sunset #night #summer #nofilterneeded #nofilter #nofilterscotland #visitscotland #instascotland #ig_scot #lovescotland #greatnorthcollective #thegreatoutdoors #ig_today #scotspirit #photosofbritain #visualsoflife","code":"BV_-cK4FpqM","dimensions":{"height":1080,"width":1080},"display_url":"https://scontent-lht6-1.cdninstagram.com/vp/099a251a7779a4e2dc88cdf45b7a4629/5B1624B6/t51.2885-15/e35/19622908_1476955395729184_5789754062631075840_n.jpg","id":"1549231411546200716","is_video":false,"location":{"has_public_page":true,"id":"972736504","name":"Lochboisdale Harbour","slug":"lochboisdale-harbour"},"media_url":"https://scontent-lht6-1.cdninstagram.com/vp/099a251a7779a4e2dc88cdf45b7a4629/5B1624B6/t51.2885-15/e35/19622908_1476955395729184_5789754062631075840_n.jpg","post_url":"https://www.instagram.com/p/BV_-cK4FpqM","tags":["#calmac","#ferry","#sea","#westernisles","#scotland","#holiday","#evening","#sunset","#night","#summer","#nofilterneeded","#nofilter","#nofilterscotland","#visitscotland","#instascotland","#ig_scot","#lovescotland","#greatnorthcollective","#thegreatoutdoors","#ig_today","#scotspirit","#photosofbritain","#visualsoflife"],"timestamp":1498902797,"FullID":"2017-07-01-1549231411546200716","lat":57.1610489,"long":-7.3405499,"location_count":1},{"caption":"This dog walks himself, owner was about a mile off while he charged up and down.\n.\n.\n.\n#dog #sea #beach #waves #enniscrone #enniscronebeach #ireland #sunset #dusk #sun #motion","code":"BUzlWbKgOPD","dimensions":{"height":1080,"width":1080},"display_url":"https://scontent-lht6-1.cdninstagram.com/vp/58771c1f30cc6b99cda7b0fad100ca53/5B17B3A0/t51.2885-15/e35/18812226_156254268247529_5408047021816807424_n.jpg","id":"1527728967325377475","is_video":false,"location":{"has_public_page":true,"id":"3615984","name":"Enniscrone Beach","slug":"enniscrone-beach"},"media_url":"https://scontent-lht6-1.cdninstagram.com/vp/58771c1f30cc6b99cda7b0fad100ca53/5B17B3A0/t51.2885-15/e35/18812226_156254268247529_5408047021816807424_n.jpg","post_url":"https://www.instagram.com/p/BUzlWbKgOPD","tags":["#dog","#sea","#beach","#waves","#enniscrone","#enniscronebeach","#ireland","#sunset","#dusk","#sun","#motion"],"timestamp":1496339506,"FullID":"2017-06-01-1527728967325377475","lat":54.2117184391,"long":-9.0991955996,"location_count":5},{"caption":"Bird above the sea\n.\n.\n.\n#bird #seascape #landscape #sea #beach #reflection #clouds #cloudy #atmosperic #atmosphere #ireland #enniscrone #enniscronebeach #sunset #yellow #latergram #picoftheday #nofilterneeded #nofilter #mayo","code":"BUoXJqdgNkH","dimensions":{"height":1080,"width":1080},"display_url":"https://scontent-lht6-1.cdninstagram.com/vp/7a6e0ab47b3ba836a3eb03bbf7c1ab61/5B0986C8/t51.2885-15/e35/18722843_165746323960272_934819066701414400_n.jpg","id":"1524570293002098951","is_video":false,"location":{"has_public_page":true,"id":"3615984","name":"Enniscrone Beach","slug":"enniscrone-beach"},"media_url":"https://scontent-lht6-1.cdninstagram.com/vp/7a6e0ab47b3ba836a3eb03bbf7c1ab61/5B0986C8/t51.2885-15/e35/18722843_165746323960272_934819066701414400_n.jpg","post_url":"https://www.instagram.com/p/BUoXJqdgNkH","tags":["#bird","#seascape","#landscape","#sea","#beach","#reflection","#clouds","#cloudy","#atmosperic","#atmosphere","#ireland","#enniscrone","#enniscronebeach","#sunset","#yellow","#latergram","#picoftheday","#nofilterneeded","#nofilter","#mayo"],"timestamp":1495962963,"FullID":"2017-05-28-1524570293002098951","lat":54.2117184391,"long":-9.0991955996,"location_count":5},{"caption":"Spire\n.\n.\n.\n#sunset #dusk #architecture #spire #tower #skyline #silhouette #sky #cloud #clouds #skyporn #blue #calm #peace #night #instalondon #igerslondon #picoftheday #nofilter #london #broadgate #shoreditch #eastlondon","code":"BRKzEFmg_73","dimensions":{"height":1080,"width":1080},"display_url":"https://scontent-lht6-1.cdninstagram.com/vp/c251c436c5296034e290f8aa3cafb927/5B1D6240/t51.2885-15/e35/17076290_626525554200511_4684841221422579712_n.jpg","id":"1462205610300014327","is_video":false,"location":{"has_public_page":true,"id":"223196746","name":"Broadgate","slug":"broadgate"},"media_url":"https://scontent-lht6-1.cdninstagram.com/vp/c251c436c5296034e290f8aa3cafb927/5B1D6240/t51.2885-15/e35/17076290_626525554200511_4684841221422579712_n.jpg","post_url":"https://www.instagram.com/p/BRKzEFmg_73","tags":["#sunset","#dusk","#architecture","#spire","#tower","#skyline","#silhouette","#sky","#cloud","#clouds","#skyporn","#blue","#calm","#peace","#night","#instalondon","#igerslondon","#picoftheday","#nofilter","#london","#broadgate","#shoreditch","#eastlondon"],"timestamp":1488528513,"FullID":"2017-03-03-1462205610300014327","lat":51.519,"long":-0.0835,"location_count":22},{"caption":"#bench #evening #sunset #nofilter #picoftheday #latergram #nature","code":"BPw2aM_B3Vw","dimensions":{"height":1080,"width":1080},"display_url":"https://scontent-lht6-1.cdninstagram.com/vp/06a683bf3c0e3bfc994e898ac3726db3/5B1E930A/t51.2885-15/e35/16110452_1837436193177276_5370303012428316672_n.jpg","id":"1436887576291538288","is_video":false,"location":{"has_public_page":true,"id":"403087946","name":"Barnes, London","slug":"barnes-london"},"media_url":"https://scontent-lht6-1.cdninstagram.com/vp/06a683bf3c0e3bfc994e898ac3726db3/5B1E930A/t51.2885-15/e35/16110452_1837436193177276_5370303012428316672_n.jpg","post_url":"https://www.instagram.com/p/BPw2aM_B3Vw","tags":["#bench","#evening","#sunset","#nofilter","#picoftheday","#latergram","#nature"],"timestamp":1485510368,"FullID":"2017-01-27-1436887576291538288","lat":51.4741,"long":-0.2352,"location_count":1},{"caption":"Culbin Beach Glow - #beach #sunset #scotland #landscape #sea #sky","code":"BOvHMLHBs36","dimensions":{"height":1080,"width":1080},"display_url":"https://scontent-lht6-1.cdninstagram.com/vp/445785571301783175028af2e41eecae/5B2706DE/t51.2885-15/e35/15875941_366072893773556_3824224964664360960_n.jpg","id":"1418384030533340666","is_video":false,"location":{"has_public_page":true,"id":"337750034","name":"Culbin Forest","slug":"culbin-forest"},"media_url":"https://scontent-lht6-1.cdninstagram.com/vp/445785571301783175028af2e41eecae/5B2706DE/t51.2885-15/e35/15875941_366072893773556_3824224964664360960_n.jpg","post_url":"https://www.instagram.com/p/BOvHMLHBs36","tags":["#beach","#sunset","#scotland","#landscape","#sea","#sky"],"timestamp":1483304574,"FullID":"2017-01-01-1418384030533340666","lat":57.637624,"long":-3.5652875,"location_count":25},{"caption":"Through the Trees Again - #trees #sunset #light #dark","code":"BOu5tWgB3dU","dimensions":{"height":1080,"width":1080},"display_url":"https://scontent-lht6-1.cdninstagram.com/vp/b21ad58aa899b404867f1f440cafd0b9/5B10B3A2/t51.2885-15/e35/15803723_851433534959609_7102406552027398144_n.jpg","id":"1418324737855551316","is_video":false,"location":{"has_public_page":true,"id":"337750034","name":"Culbin Forest","slug":"culbin-forest"},"media_url":"https://scontent-lht6-1.cdninstagram.com/vp/b21ad58aa899b404867f1f440cafd0b9/5B10B3A2/t51.2885-15/e35/15803723_851433534959609_7102406552027398144_n.jpg","post_url":"https://www.instagram.com/p/BOu5tWgB3dU","tags":["#trees","#sunset","#light","#dark"],"timestamp":1483297506,"FullID":"2017-01-01-1418324737855551316","lat":57.637624,"long":-3.5652875,"location_count":25},{"caption":"Through the trees at Culbin Forest - #silhouette #clouds #sky #forest #trees #sun #light #sunset #dusk","code":"BOu2CZYBx2_","dimensions":{"height":1080,"width":1080},"display_url":"https://scontent-lht6-1.cdninstagram.com/vp/c44abe266dc8fe2edf9daf9f4ae4530b/5B0BB4BA/t51.2885-15/e35/15802678_397504693926955_5375636597305769984_n.jpg","id":"1418308591865503167","is_video":false,"location":{"has_public_page":true,"id":"337750034","name":"Culbin Forest","slug":"culbin-forest"},"media_url":"https://scontent-lht6-1.cdninstagram.com/vp/c44abe266dc8fe2edf9daf9f4ae4530b/5B0BB4BA/t51.2885-15/e35/15802678_397504693926955_5375636597305769984_n.jpg","post_url":"https://www.instagram.com/p/BOu2CZYBx2_","tags":["#silhouette","#clouds","#sky","#forest","#trees","#sun","#light","#sunset","#dusk"],"timestamp":1483295581,"FullID":"2017-01-01-1418308591865503167","lat":57.637624,"long":-3.5652875,"location_count":25},{"caption":"Dune Sunset at Culbin Beach - #dune #sanddune #forest #sunset #sky #landscape #clouds #orange #cloud #sun #nofilter","code":"BOu1aX0hx-M","dimensions":{"height":1080,"width":1080},"display_url":"https://scontent-lht6-1.cdninstagram.com/vp/6772df952bc4e09a611b65924acd663d/5B08BAFD/t51.2885-15/e35/15802153_699944430165764_8295021706297212928_n.jpg","id":"1418305841417101196","is_video":false,"location":{"has_public_page":true,"id":"337750034","name":"Culbin Forest","slug":"culbin-forest"},"media_url":"https://scontent-lht6-1.cdninstagram.com/vp/6772df952bc4e09a611b65924acd663d/5B08BAFD/t51.2885-15/e35/15802153_699944430165764_8295021706297212928_n.jpg","post_url":"https://www.instagram.com/p/BOu1aX0hx-M","tags":["#dune","#sanddune","#forest","#sunset","#sky","#landscape","#clouds","#orange","#cloud","#sun","#nofilter"],"timestamp":1483295253,"FullID":"2017-01-01-1418305841417101196","lat":57.637624,"long":-3.5652875,"location_count":25},{"caption":"#Aberdeenshire #Scotland #landscape #sunset #clouds #farm #farmland","code":"BML6-Reh4ne","dimensions":{"height":1080,"width":1080},"display_url":"https://scontent-lht6-1.cdninstagram.com/vp/38355f66e00555cd73b9cd8b8efbb5ad/5B1892B1/t51.2885-15/e35/14711962_204523773308502_7274174165484044288_n.jpg","id":"1372449877535459806","is_video":false,"location":{"has_public_page":true,"id":"847544201","name":"Mulbuie","slug":"mulbuie"},"media_url":"https://scontent-lht6-1.cdninstagram.com/vp/38355f66e00555cd73b9cd8b8efbb5ad/5B1892B1/t51.2885-15/e35/14711962_204523773308502_7274174165484044288_n.jpg","post_url":"https://www.instagram.com/p/BML6-Reh4ne","tags":["#Aberdeenshire","#Scotland","#landscape","#sunset","#clouds","#farm","#farmland"],"timestamp":1477828796,"FullID":"2016-10-30-1372449877535459806","lat":57.5406396333,"long":-4.4284455333,"location_count":217},{"caption":"#sky #sunset #sculpture #architecture","code":"BLy2nUlBYQL","dimensions":{"height":1080,"width":1080},"display_url":"https://scontent-lht6-1.cdninstagram.com/vp/42d48fe09499bb3c9db367da2f888af5/5B277D4F/t51.2885-15/e35/14723661_1933485830212367_2156549997544341504_n.jpg","id":"1365393833713828875","is_video":false,"location":{"has_public_page":true,"id":"213069183","name":"The O2","slug":"the-o2"},"media_url":"https://scontent-lht6-1.cdninstagram.com/vp/42d48fe09499bb3c9db367da2f888af5/5B277D4F/t51.2885-15/e35/14723661_1933485830212367_2156549997544341504_n.jpg","post_url":"https://www.instagram.com/p/BLy2nUlBYQL","tags":["#sky","#sunset","#sculpture","#architecture"],"timestamp":1476987650,"FullID":"2016-10-20-1365393833713828875","lat":51.5025883353,"long":0.0043592565,"location_count":1},{"caption":"#track #sunset #path #fence #orange #night #sky #landscape","code":"BH7BCk_hIx5","dimensions":{"height":1080,"width":1080},"display_url":"https://scontent-lht6-1.cdninstagram.com/vp/cd0fcf848c04ba4248eda80f09303a39/5B0AFEC1/t51.2885-15/e35/13744066_600411813460727_740723987_n.jpg","id":"1295633893004971129","is_video":false,"location":{"has_public_page":true,"id":"1029615837","name":"South Uist","slug":"south-uist"},"media_url":"https://scontent-lht6-1.cdninstagram.com/vp/cd0fcf848c04ba4248eda80f09303a39/5B0AFEC1/t51.2885-15/e35/13744066_600411813460727_740723987_n.jpg","post_url":"https://www.instagram.com/p/BH7BCk_hIx5","tags":["#track","#sunset","#path","#fence","#orange","#night","#sky","#landscape"],"timestamp":1468671617,"FullID":"2016-07-16-1295633893004971129","lat":57.2666666667,"long":-7.3166666667,"location_count":68},{"caption":"#sunset #again #sky #landscape #beach #gradient #reflection #night #orange","code":"BH60QvIhVsb","dimensions":{"height":1080,"width":1080},"display_url":"https://scontent-lht6-1.cdninstagram.com/vp/f1f1318b12e1bde05a1c0a4025192599/5B18CEFE/t51.2885-15/e35/13734422_1754511714766213_963103546_n.jpg","id":"1295577691361467163","is_video":false,"location":{"has_public_page":true,"id":"1029615837","name":"South Uist","slug":"south-uist"},"media_url":"https://scontent-lht6-1.cdninstagram.com/vp/f1f1318b12e1bde05a1c0a4025192599/5B18CEFE/t51.2885-15/e35/13734422_1754511714766213_963103546_n.jpg","post_url":"https://www.instagram.com/p/BH60QvIhVsb","tags":["#sunset","#again","#sky","#landscape","#beach","#gradient","#reflection","#night","#orange"],"timestamp":1468664917,"FullID":"2016-07-16-1295577691361467163","lat":57.2666666667,"long":-7.3166666667,"location_count":68},{"caption":"#clouds #rocks #beach #sky #sunset","code":"BHzjwY2BnVM","dimensions":{"height":1080,"width":1080},"display_url":"https://scontent-lht6-1.cdninstagram.com/vp/1bb20fc3ac4fe6cbfba462ec8451a04a/5B1AA92A/t51.2885-15/e35/13671128_1182311078495220_1730807633_n.jpg","id":"1293534774824432972","is_video":false,"location":{"has_public_page":true,"id":"1029615837","name":"South Uist","slug":"south-uist"},"media_url":"https://scontent-lht6-1.cdninstagram.com/vp/1bb20fc3ac4fe6cbfba462ec8451a04a/5B1AA92A/t51.2885-15/e35/13671128_1182311078495220_1730807633_n.jpg","post_url":"https://www.instagram.com/p/BHzjwY2BnVM","tags":["#clouds","#rocks","#beach","#sky","#sunset"],"timestamp":1468421383,"FullID":"2016-07-13-1293534774824432972","lat":57.2666666667,"long":-7.3166666667,"location_count":68},{"caption":"#oystercatcher #bird #landscape #sky #sea #sunset","code":"BHzjvAEhzyX","dimensions":{"height":1080,"width":1080},"display_url":"https://scontent-lht6-1.cdninstagram.com/vp/a99ccccf4e879e9f88469dda19ea6c00/5B0BF617/t51.2885-15/e35/13671256_912470055546985_1461197582_n.jpg","id":"1293534679504731287","is_video":false,"location":{"has_public_page":true,"id":"1029615837","name":"South Uist","slug":"south-uist"},"media_url":"https://scontent-lht6-1.cdninstagram.com/vp/a99ccccf4e879e9f88469dda19ea6c00/5B0BF617/t51.2885-15/e35/13671256_912470055546985_1461197582_n.jpg","post_url":"https://www.instagram.com/p/BHzjvAEhzyX","tags":["#oystercatcher","#bird","#landscape","#sky","#sea","#sunset"],"timestamp":1468421371,"FullID":"2016-07-13-1293534679504731287","lat":57.2666666667,"long":-7.3166666667,"location_count":68},{"caption":"#beach #sunset #reflection #clouds #sky","code":"BHxtU1cB88w","dimensions":{"height":1080,"width":1080},"display_url":"https://scontent-lht6-1.cdninstagram.com/vp/548a6493d4b7b77dc103db7baa719942/5B2778E5/t51.2885-15/e35/13658870_1570005213302305_1975952116_n.jpg","id":"1293013911893167920","is_video":false,"location":{"has_public_page":true,"id":"1029615837","name":"South Uist","slug":"south-uist"},"media_url":"https://scontent-lht6-1.cdninstagram.com/vp/548a6493d4b7b77dc103db7baa719942/5B2778E5/t51.2885-15/e35/13658870_1570005213302305_1975952116_n.jpg","post_url":"https://www.instagram.com/p/BHxtU1cB88w","tags":["#beach","#sunset","#reflection","#clouds","#sky"],"timestamp":1468359291,"FullID":"2016-07-12-1293013911893167920","lat":57.2666666667,"long":-7.3166666667,"location_count":68},{"caption":"#beach #reflection #water #sea #clouds #sunset #orange","code":"BHxtKO1hIvv","dimensions":{"height":1080,"width":1080},"display_url":"https://scontent-lht6-1.cdninstagram.com/vp/9e57d380983e82aad0d22abc806858d4/5B47A6A7/t51.2885-15/e35/13671217_1748546665414585_939132933_n.jpg","id":"1293013183250074607","is_video":false,"location":{"has_public_page":true,"id":"1029615837","name":"South Uist","slug":"south-uist"},"media_url":"https://scontent-lht6-1.cdninstagram.com/vp/9e57d380983e82aad0d22abc806858d4/5B47A6A7/t51.2885-15/e35/13671217_1748546665414585_939132933_n.jpg","post_url":"https://www.instagram.com/p/BHxtKO1hIvv","tags":["#beach","#reflection","#water","#sea","#clouds","#sunset","#orange"],"timestamp":1468359204,"FullID":"2016-07-12-1293013183250074607","lat":57.2666666667,"long":-7.3166666667,"location_count":68},{"caption":"#sky #clouds #sunset #red #orange","code":"BHAyRIym2Z6","dimensions":{"height":1080,"width":1080},"display_url":"https://scontent-lht6-1.cdninstagram.com/vp/96ea70917313ac6762d1e6f81cda780a/5B19F383/t51.2885-15/e35/13397470_288600628154675_179511884_n.jpg","id":"1279243374168860282","is_video":false,"location":{"has_public_page":true,"id":"847544201","name":"Mulbuie","slug":"mulbuie"},"media_url":"https://scontent-lht6-1.cdninstagram.com/vp/96ea70917313ac6762d1e6f81cda780a/5B19F383/t51.2885-15/e35/13397470_288600628154675_179511884_n.jpg","post_url":"https://www.instagram.com/p/BHAyRIym2Z6","tags":["#sky","#clouds","#sunset","#red","#orange"],"timestamp":1466717715,"FullID":"2016-06-23-1279243374168860282","lat":57.5406396333,"long":-4.4284455333,"location_count":217},{"caption":"#sky #clouds #grass #sunset","code":"BHAq28iG2Vn","dimensions":{"height":1080,"width":1080},"display_url":"https://scontent-lht6-1.cdninstagram.com/vp/1af1f2e11803f0ae90e8832c2b10c32c/5B0D4551/t51.2885-15/e35/13413483_234895116897030_1369668022_n.jpg","id":"1279210787975161191","is_video":false,"location":{"has_public_page":true,"id":"847544201","name":"Mulbuie","slug":"mulbuie"},"media_url":"https://scontent-lht6-1.cdninstagram.com/vp/1af1f2e11803f0ae90e8832c2b10c32c/5B0D4551/t51.2885-15/e35/13413483_234895116897030_1369668022_n.jpg","post_url":"https://www.instagram.com/p/BHAq28iG2Vn","tags":["#sky","#clouds","#grass","#sunset"],"timestamp":1466713830,"FullID":"2016-06-23-1279210787975161191","lat":57.5406396333,"long":-4.4284455333,"location_count":217},{"caption":"#fisheye #horse #field #sunset #sun #sky #clouds","code":"BACn28hG2To","dimensions":{"height":1080,"width":1080},"display_url":"https://scontent-lht6-1.cdninstagram.com/vp/19656fb07b5d1cd1f591f28a263ebef4/5B1A3D88/t51.2885-15/e35/10413224_936237109785846_143776835_n.jpg","id":"1153659754205897960","is_video":false,"location":{"has_public_page":true,"id":"104028229","name":"Big Sky Lodges","slug":"big-sky-lodges"},"media_url":"https://scontent-lht6-1.cdninstagram.com/vp/19656fb07b5d1cd1f591f28a263ebef4/5B1A3D88/t51.2885-15/e35/10413224_936237109785846_143776835_n.jpg","post_url":"https://www.instagram.com/p/BACn28hG2To","tags":["#fisheye","#horse","#field","#sunset","#sun","#sky","#clouds"],"timestamp":1451746981,"FullID":"2016-01-02-1153659754205897960","lat":57.5302580332,"long":-4.4134503112,"location_count":7},{"caption":"#sunset #firth #beauly","code":"70UELYm2fS","dimensions":{"height":1080,"width":1080},"display_url":"https://scontent-lht6-1.cdninstagram.com/vp/5cabf6bac810df8afc2f9836864d9a72/5B1D2BF5/t51.2885-15/e35/11849337_1626465127618644_2086357598_n.jpg","id":"1077574458880518098","is_video":false,"location":{"has_public_page":true,"id":"1551967","name":"Kessock Bridge","slug":"kessock-bridge"},"media_url":"https://scontent-lht6-1.cdninstagram.com/vp/5cabf6bac810df8afc2f9836864d9a72/5B1D2BF5/t51.2885-15/e35/11849337_1626465127618644_2086357598_n.jpg","post_url":"https://www.instagram.com/p/70UELYm2fS","tags":["#sunset","#firth","#beauly"],"timestamp":1442676907,"FullID":"2015-09-19-1077574458880518098","lat":57.49916667,"long":-4.22944444,"location_count":3},{"caption":"#orange #flats #architecture #sunset","code":"2bu7A1m2Z7","dimensions":{"height":640,"width":640},"display_url":"https://scontent-lht6-1.cdninstagram.com/vp/01f4a212f8c4eb5649275082300a0c2a/5B2CCD71/t51.2885-15/e15/11247563_1589114061377723_688015368_n.jpg","id":"980583709371229819","is_video":false,"location":{"has_public_page":true,"id":"358582079","name":"Seaton, Aberdeen","slug":"seaton-aberdeen"},"media_url":"https://scontent-lht6-1.cdninstagram.com/vp/01f4a212f8c4eb5649275082300a0c2a/5B2CCD71/t51.2885-15/e15/11247563_1589114061377723_688015368_n.jpg","post_url":"https://www.instagram.com/p/2bu7A1m2Z7","tags":["#orange","#flats","#architecture","#sunset"],"timestamp":1431114708,"FullID":"2015-05-08-980583709371229819","lat":57.167867602,"long":-2.0892221075,"location_count":26},{"caption":"#noeffect #sunset #sky","code":"1oQO2pm2V0","dimensions":{"height":640,"width":640},"display_url":"https://scontent-lht6-1.cdninstagram.com/vp/8573194588c87c21962ff5325b24324a/5B1362A3/t51.2885-15/e15/11084750_811028558950985_254412081_n.jpg","id":"966093509567931764","is_video":false,"location":{"has_public_page":true,"id":"847544201","name":"Mulbuie","slug":"mulbuie"},"media_url":"https://scontent-lht6-1.cdninstagram.com/vp/8573194588c87c21962ff5325b24324a/5B1362A3/t51.2885-15/e15/11084750_811028558950985_254412081_n.jpg","post_url":"https://www.instagram.com/p/1oQO2pm2V0","tags":["#noeffect","#sunset","#sky"],"timestamp":1429387342,"FullID":"2015-04-18-966093509567931764","lat":57.5406396333,"long":-4.4284455333,"location_count":217},{"caption":"#landscape #sky #clouds #sunset #farm #lane #track #road","code":"1lrTypm2bN","dimensions":{"height":640,"width":640},"display_url":"https://scontent-lht6-1.cdninstagram.com/vp/65e683c2b9b718aae67bb1f063ffcf78/5B0897AC/t51.2885-15/e15/11111240_1610168289220924_1732357912_n.jpg","id":"965368171196016333","is_video":false,"location":{"has_public_page":true,"id":"847544201","name":"Mulbuie","slug":"mulbuie"},"media_url":"https://scontent-lht6-1.cdninstagram.com/vp/65e683c2b9b718aae67bb1f063ffcf78/5B0897AC/t51.2885-15/e15/11111240_1610168289220924_1732357912_n.jpg","post_url":"https://www.instagram.com/p/1lrTypm2bN","tags":["#landscape","#sky","#clouds","#sunset","#farm","#lane","#track","#road"],"timestamp":1429300875,"FullID":"2015-04-17-965368171196016333","lat":57.5406396333,"long":-4.4284455333,"location_count":217},{"caption":"#stubble #field #sky #sunset #clouds #landscape","code":"1lof39m2VO","dimensions":{"height":640,"width":640},"display_url":"https://scontent-lht6-1.cdninstagram.com/vp/59ce06fde92443391b4a935536460427/5B17264A/t51.2885-15/e15/11117163_711725302269490_951134328_n.jpg","id":"965355807394456910","is_video":false,"location":{"has_public_page":true,"id":"847544201","name":"Mulbuie","slug":"mulbuie"},"media_url":"https://scontent-lht6-1.cdninstagram.com/vp/59ce06fde92443391b4a935536460427/5B17264A/t51.2885-15/e15/11117163_711725302269490_951134328_n.jpg","post_url":"https://www.instagram.com/p/1lof39m2VO","tags":["#stubble","#field","#sky","#sunset","#clouds","#landscape"],"timestamp":1429299401,"FullID":"2015-04-17-965355807394456910","lat":57.5406396333,"long":-4.4284455333,"location_count":217},{"caption":"#epic #HDR #landscape #road #clouds #sky #sunset","code":"1loQRxm2Us","dimensions":{"height":640,"width":640},"display_url":"https://scontent-lht6-1.cdninstagram.com/vp/0568d68eed4b2a2d8256810cb1af9b23/5B4C0CA1/t51.2885-15/e15/11111234_622978527837457_926504551_n.jpg","id":"965354735598789932","is_video":false,"location":{"has_public_page":true,"id":"847544201","name":"Mulbuie","slug":"mulbuie"},"media_url":"https://scontent-lht6-1.cdninstagram.com/vp/0568d68eed4b2a2d8256810cb1af9b23/5B4C0CA1/t51.2885-15/e15/11111234_622978527837457_926504551_n.jpg","post_url":"https://www.instagram.com/p/1loQRxm2Us","tags":["#epic","#HDR","#landscape","#road","#clouds","#sky","#sunset"],"timestamp":1429299273,"FullID":"2015-04-17-965354735598789932","lat":57.5406396333,"long":-4.4284455333,"location_count":217},{"caption":"#horse #field #sky #clouds #landscape #sunset","code":"1lnrHbG2TW","dimensions":{"height":640,"width":640},"display_url":"https://scontent-lht6-1.cdninstagram.com/vp/b46440598ebfd3b692d9dc8a751e3979/5B280FF8/t51.2885-15/e15/10932301_485906371562812_939174225_n.jpg","id":"965352181863245014","is_video":false,"location":{"has_public_page":true,"id":"847544201","name":"Mulbuie","slug":"mulbuie"},"media_url":"https://scontent-lht6-1.cdninstagram.com/vp/b46440598ebfd3b692d9dc8a751e3979/5B280FF8/t51.2885-15/e15/10932301_485906371562812_939174225_n.jpg","post_url":"https://www.instagram.com/p/1lnrHbG2TW","tags":["#horse","#field","#sky","#clouds","#landscape","#sunset"],"timestamp":1429298969,"FullID":"2015-04-17-965352181863245014","lat":57.5406396333,"long":-4.4284455333,"location_count":217},{"caption":"#landscape #sunset #orange #sky #clouds #tree","code":"1lnd0kG2S8","dimensions":{"height":640,"width":640},"display_url":"https://scontent-lht6-1.cdninstagram.com/vp/d5126fb9eae79371d1f0b26653d70bdd/5B2A3F2C/t51.2885-15/e15/10584748_1389839941340880_556191839_n.jpg","id":"965351268259947708","is_video":false,"location":{"has_public_page":true,"id":"847544201","name":"Mulbuie","slug":"mulbuie"},"media_url":"https://scontent-lht6-1.cdninstagram.com/vp/d5126fb9eae79371d1f0b26653d70bdd/5B2A3F2C/t51.2885-15/e15/10584748_1389839941340880_556191839_n.jpg","post_url":"https://www.instagram.com/p/1lnd0kG2S8","tags":["#landscape","#sunset","#orange","#sky","#clouds","#tree"],"timestamp":1429298860,"FullID":"2015-04-17-965351268259947708","lat":57.5406396333,"long":-4.4284455333,"location_count":217},{"caption":"#blast #sunset #sun #sky #field #farm #croft #scotland #clouds","code":"dU5A8fG2UZ","dimensions":{"height":612,"width":612},"display_url":"https://scontent-lht6-1.cdninstagram.com/vp/cacb71906d1c2fb6ebbaed521556f29e/5B16173F/t51.2885-15/e15/11312340_1454037334890514_2041685869_n.jpg","id":"528297809906722073","is_video":false,"location":{"has_public_page":true,"id":"847544201","name":"Mulbuie","slug":"mulbuie"},"media_url":"https://scontent-lht6-1.cdninstagram.com/vp/cacb71906d1c2fb6ebbaed521556f29e/5B16173F/t51.2885-15/e15/11312340_1454037334890514_2041685869_n.jpg","post_url":"https://www.instagram.com/p/dU5A8fG2UZ","tags":["#blast","#sunset","#sun","#sky","#field","#farm","#croft","#scotland","#clouds"],"timestamp":1377198028,"FullID":"2013-08-22-528297809906722073","lat":57.5406396333,"long":-4.4284455333,"location_count":217},{"caption":"#golden #grass #hay #field #evening #summer #gold #Sun #light #sky #clouds #cloud #blue #sunset #evening","code":"che0hgm2dT","dimensions":{"height":612,"width":612},"display_url":"https://scontent-lht6-1.cdninstagram.com/vp/7841ed1b43ced50bc533413c525bc973/5B0B161C/t51.2885-15/e15/11352080_720375131441026_606858264_n.jpg","id":"513827383285606227","is_video":false,"location":{"has_public_page":true,"id":"847544201","name":"Mulbuie","slug":"mulbuie"},"media_url":"https://scontent-lht6-1.cdninstagram.com/vp/7841ed1b43ced50bc533413c525bc973/5B0B161C/t51.2885-15/e15/11352080_720375131441026_606858264_n.jpg","post_url":"https://www.instagram.com/p/che0hgm2dT","tags":["#golden","#grass","#hay","#field","#evening","#summer","#gold","#Sun","#light","#sky","#clouds","#cloud","#blue","#sunset"],"timestamp":1375473019,"FullID":"2013-08-02-513827383285606227","lat":57.5406396333,"long":-4.4284455333,"location_count":217},{"caption":"#glowing #sunset #instasky #sky #flowers #instagood","code":"cSKfCxG2Zk","dimensions":{"height":612,"width":612},"display_url":"https://scontent-lht6-1.cdninstagram.com/vp/2cbb152b5edbf4e75731a65bd2c2afc9/5B4A8B7C/t51.2885-15/e15/11351822_1615564405357167_1204047337_n.jpg","id":"509515821586540132","is_video":false,"location":{"has_public_page":true,"id":"847544201","name":"Mulbuie","slug":"mulbuie"},"media_url":"https://scontent-lht6-1.cdninstagram.com/vp/2cbb152b5edbf4e75731a65bd2c2afc9/5B4A8B7C/t51.2885-15/e15/11351822_1615564405357167_1204047337_n.jpg","post_url":"https://www.instagram.com/p/cSKfCxG2Zk","tags":["#glowing","#sunset","#instasky","#sky","#flowers","#instagood"],"timestamp":1374959040,"FullID":"2013-07-27-509515821586540132","lat":57.5406396333,"long":-4.4284455333,"location_count":217},{"caption":"Country Lane #lane #road #landscape #field #green #sunset #Amaro #nature #picoftheday","code":"bCoI-wG2ef","dimensions":{"height":612,"width":612},"display_url":"https://scontent-lht6-1.cdninstagram.com/vp/15faffbc0b9b10a17f20cb039ab4e8a7/5B2B08CD/t51.2885-15/e15/11288057_1621986761406929_914494687_n.jpg","id":"487128248704788383","is_video":false,"location":{"has_public_page":true,"id":"847544201","name":"Mulbuie","slug":"mulbuie"},"media_url":"https://scontent-lht6-1.cdninstagram.com/vp/15faffbc0b9b10a17f20cb039ab4e8a7/5B2B08CD/t51.2885-15/e15/11288057_1621986761406929_914494687_n.jpg","post_url":"https://www.instagram.com/p/bCoI-wG2ef","tags":["#lane","#road","#landscape","#field","#green","#sunset","#Amaro","#nature","#picoftheday"],"timestamp":1372290234,"FullID":"2013-06-27-487128248704788383","lat":57.5406396333,"long":-4.4284455333,"location_count":217},{"caption":"#sunset #sunrise #sun #pretty #beautiful #red #orange #blue #sky #nature #clouds #horizon  #instagood #gorgeous #warm #view #night #morning #silhouette #instasky #all_sunsets","code":"a_2fPQm2S8","dimensions":{"height":612,"width":612},"display_url":"https://scontent-lht6-1.cdninstagram.com/vp/67c142988413b5ad6935da10830cdabd/5B2D3D21/t51.2885-15/e15/11261132_996124197066281_175536951_n.jpg","id":"486346925979428028","is_video":false,"location":{"has_public_page":true,"id":"847544201","name":"Mulbuie","slug":"mulbuie"},"media_url":"https://scontent-lht6-1.cdninstagram.com/vp/67c142988413b5ad6935da10830cdabd/5B2D3D21/t51.2885-15/e15/11261132_996124197066281_175536951_n.jpg","post_url":"https://www.instagram.com/p/a_2fPQm2S8","tags":["#sunset","#sunrise","#sun","#pretty","#beautiful","#red","#orange","#blue","#sky","#nature","#clouds","#horizon","#instagood","#gorgeous","#warm","#view","#night","#morning","#silhouette","#instasky","#all_sunsets"],"timestamp":1372197093,"FullID":"2013-06-25-486346925979428028","lat":57.5406396333,"long":-4.4284455333,"location_count":217},{"caption":"#sunset #sun #beautiful #red #orange #pink #sky #nature #clouds #horizon #instagood #gorgeous #warm #view #night #silhouette #instasky #all_sunsets","code":"a9I9HkG2Wb","dimensions":{"height":612,"width":612},"display_url":"https://scontent-lht6-1.cdninstagram.com/vp/ed6debfaac69c77aab3982fa80719821/5B0FC98C/t51.2885-15/e15/11274422_1089269341103138_607481157_n.jpg","id":"485583719208019355","is_video":false,"location":{"has_public_page":true,"id":"847544201","name":"Mulbuie","slug":"mulbuie"},"media_url":"https://scontent-lht6-1.cdninstagram.com/vp/ed6debfaac69c77aab3982fa80719821/5B0FC98C/t51.2885-15/e15/11274422_1089269341103138_607481157_n.jpg","post_url":"https://www.instagram.com/p/a9I9HkG2Wb","tags":["#sunset","#sun","#beautiful","#red","#orange","#pink","#sky","#nature","#clouds","#horizon","#instagood","#gorgeous","#warm","#view","#night","#silhouette","#instasky","#all_sunsets"],"timestamp":1372106111,"FullID":"2013-06-24-485583719208019355","lat":57.5406396333,"long":-4.4284455333,"location_count":217},{"caption":"'Wyvis' #Munro #hill #hillrun #fellrunning #sunset #hillwalking #clouds #sky #skyscape","code":"Z3nG_Gm2YH","dimensions":{"height":612,"width":612},"display_url":"https://scontent-lht6-1.cdninstagram.com/vp/2daa61599ad0c0ef57d8b870af4c6346/5B1AE7D4/t51.2885-15/e15/11269664_824967080922238_1460998422_n.jpg","id":"466013090343511559","is_video":false,"location":{"has_public_page":true,"id":"280000444","name":"Ben Wyvis","slug":"ben-wyvis"},"media_url":"https://scontent-lht6-1.cdninstagram.com/vp/2daa61599ad0c0ef57d8b870af4c6346/5B1AE7D4/t51.2885-15/e15/11269664_824967080922238_1460998422_n.jpg","post_url":"https://www.instagram.com/p/Z3nG_Gm2YH","tags":["#Munro","#hill","#hillrun","#fellrunning","#sunset","#hillwalking","#clouds","#sky","#skyscape"],"timestamp":1369773111,"FullID":"2013-05-28-466013090343511559","lat":57.6791194444,"long":-4.5792194444,"location_count":10},{"caption":"'Heights' #hills #Dingwall #Scotland #grass #sunset #evening","code":"Z3G-agm2bt","dimensions":{"height":612,"width":612},"display_url":"https://scontent-lht6-1.cdninstagram.com/vp/b1253969669664c08963a3945e5b6a2d/5B489C9B/t51.2885-15/e15/11325784_460010640820794_675701718_n.jpg","id":"465871763807102701","is_video":false,"location":{"has_public_page":true,"id":"1028906833","name":"Heights Of Fodderty","slug":"heights-of-fodderty"},"media_url":"https://scontent-lht6-1.cdninstagram.com/vp/b1253969669664c08963a3945e5b6a2d/5B489C9B/t51.2885-15/e15/11325784_460010640820794_675701718_n.jpg","post_url":"https://www.instagram.com/p/Z3G-agm2bt","tags":["#hills","#Dingwall","#Scotland","#grass","#sunset","#evening"],"timestamp":1369756263,"FullID":"2013-05-28-465871763807102701","lat":57.6073265,"long":-4.5267963333,"location_count":1},{"caption":"Sunset from Home #sunset #sky #blue #skyline #clouds","code":"XXuVpJG2Uo","dimensions":{"height":612,"width":612},"display_url":"https://scontent-lht6-1.cdninstagram.com/vp/b106c6d29ff9937b996768e40722f447/5B29AEC9/t51.2885-15/e15/11256180_1622955334586385_1741117228_n.jpg","id":"421008887607158056","is_video":false,"location":{"has_public_page":true,"id":"847544201","name":"Mulbuie","slug":"mulbuie"},"media_url":"https://scontent-lht6-1.cdninstagram.com/vp/b106c6d29ff9937b996768e40722f447/5B29AEC9/t51.2885-15/e15/11256180_1622955334586385_1741117228_n.jpg","post_url":"https://www.instagram.com/p/XXuVpJG2Uo","tags":["#sunset","#sky","#blue","#skyline","#clouds"],"timestamp":1364408192,"FullID":"2013-03-27-421008887607158056","lat":57.5406396333,"long":-4.4284455333,"location_count":217}]}