{
  "id": "822210516030809975",
  "code": "tpFBuqm2d3",
  "display_url": "https://scontent-lht6-1.cdninstagram.com/vp/2027cd720180aa540b7126731b739f73/5A92C235/t51.2885-15/e15/927460_529016963896320_1356373105_n.jpg",
  "media_url": "https://scontent-lht6-1.cdninstagram.com/vp/3f4f94863c8867e02abb5552c1b92243/5A92C87C/t50.2886-16/10719705_829537890413092_1509102904_n.mp4",
  "post_url": "https://www.instagram.com/p/tpFBuqm2d3",
  "is_video": true,
  "caption": "Speed Breakfast",
  "location": {
    "id": "358582079",
    "name": "Seaton, Aberdeen",
    "slug": "seaton-aberdeen",
    "has_public_page": true
  },
  "tags": [],
  "timestamp": 1412235153,
  "dimensions": {
    "height": 640,
    "width": 640
  }
}
