{
  "id": "1185389100234663373",
  "code": "BBzWRswG2XN",
  "display_url": "https://scontent-lht6-1.cdninstagram.com/vp/ad8edd678190dce3eca196cc074e5ce0/5B1D41F0/t51.2885-15/e35/12717010_656057437866491_1159071998_n.jpg",
  "media_url": "https://scontent-lht6-1.cdninstagram.com/vp/ad8edd678190dce3eca196cc074e5ce0/5B1D41F0/t51.2885-15/e35/12717010_656057437866491_1159071998_n.jpg",
  "post_url": "https://www.instagram.com/p/BBzWRswG2XN",
  "is_video": false,
  "caption": "#sunrise #road #reflection #snow",
  "location": {
    "id": "278032618",
    "has_public_page": true,
    "name": "Aberdeen City Beach",
    "slug": "aberdeen-city-beach"
  },
  "tags": [
    "#sunrise",
    "#road",
    "#reflection",
    "#snow"
  ],
  "timestamp": 1455529414,
  "dimensions": {
    "height": 1080,
    "width": 1080
  }
}