{
  "id": "2048021070204974356",
  "code": "BxsCE_-FTUU",
  "display_url": "https://scontent-mia3-2.cdninstagram.com/vp/0527c25f4f49696a10af975a0e66f735/5D78CAD8/t51.2885-15/e35/59990773_418771288703592_2611412063886199931_n.jpg?_nc_ht=scontent-mia3-2.cdninstagram.com",
  "media_url": "https://scontent-mia3-2.cdninstagram.com/vp/0527c25f4f49696a10af975a0e66f735/5D78CAD8/t51.2885-15/e35/59990773_418771288703592_2611412063886199931_n.jpg?_nc_ht=scontent-mia3-2.cdninstagram.com",
  "post_url": "https://www.instagram.com/p/BxsCE_-FTUU",
  "is_video": false,
  "caption": "Totem #totem #pilar #art #painting #blue #bright #colorful #teampixel",
  "location": {
    "id": "235698876",
    "name": "Santa Eulàlia, L&#x27;Hospitalet",
    "slug": "santa-eulalia-lhospitalet",
    "has_public_page": true
  },
  "tags": [
    "#totem",
    "#pilar",
    "#art",
    "#painting",
    "#blue",
    "#bright",
    "#colorful",
    "#teampixel"
  ],
  "timestamp": 1558363158,
  "dimensions": {
    "height": 1080,
    "width": 1080
  }
}